Workbook

Sheet Kriteriji
A1: Ručna provjera preciznosti upita D AND A (OpenAlex) — agrodronovi — kriteriji kodiranja
A3: Svaki zapis dobiva jednu od tri oznake:
A4: A — RELEVANTAN: zračna bespilotna letjelica (UAV/UAS/dron) je senzorska platforma, aplikator ili predmet rada, A primjena je poljoprivredna: usjevi, voćnjaci, vinogradi, travnjaci za stoku, stoka, poljoprivredno zemljište, prskanje/aplikacija, fenotipizacija, navodnjavanje, zaštita bilja, prinos; uključuje i pregledne radove o UAV-ima u poljoprivredi.
A5: B — GRANIČAN: UAV/dron jest prisutan, ali primjena nije poljoprivredna (mreže, upravljanje i navigacija, šumarstvo, rudarstvo, urbanizam, vojne primjene, dostava) ILI je UAV samo spomenut kao kontekst ili budući rad.
A6: C — NERELEVANTAN: nema zračne bespilotne letjelice („drone“ = trut, „UAS“ = Drosophila GAL4/UAS, ocjena urtikarije, sveučilišni akronim; „yield“ u nepoljoprivrednom smislu; radovi bez UAV pojma u naslovu/sažetku).
A8: Postupak: prijedlog oznake (stupac J) i obrazloženje (K) generirani su uz pomoć AI; konačnu ocjenu (L) neovisno dodjeljuje autor čitajući naslov i sažetak, a kod nedostupnog sažetka cijeli rad. Stupac N označava ostaje li zapis u ČISTOM upitu (D AND A NOT N, gdje N isključuje Drosophila/GAL4, pčele, medicinske akronime i sveučilišni naziv) — glavna serija rada je čisti upit, pa list „Sažetak“ računa preciznost samo za zapise s „da“; uzorak iz sirovog upita ograničen na čisti upit i dalje je slučajan uzorak čistog upita.
A10: Uzorci: (a) 100 slučajnih zapisa 2005.–2025. (OpenAlex sample=100, seed=20260828); (b) 50 slučajnih zapisa 2005.–2015. (seed=20260829). Dohvat 28. 8. 2026.
A12: Za rad se izvještava: preciznost P(A) i P(A ili B) čistog upita s Wilsonovim 95 % intervalom; test razlike ranog i cijelog uzorka; osjetljivost trenda na sirovi upit i na strogi upit bez ekoloških pojmova (list „Osjetljivost_upita“).

Sheet Sažetak
A1: Sažetak provjere preciznosti ČISTOG upita (samo zapisi s „da“ u stupcu N; sve formule)
A3: Uzorak A (2005.–2025.; od 100 sirovih zapisa oni u čistom upitu)
A4: n (ocijenjeno) | B4: =COUNTIFS(Uzorak_100!$L$5:$L$104,"A",Uzorak_100!$N$5:$N$104,"da")+COUNTIFS(Uzorak_100!$L$5:$L$104,"B",Uzorak_100!$N$5:$N$104,"da")+COUNTIFS(Uzorak_100!$L$5:$L$104,"C",Uzorak_100!$N$5:$N$104,"da") -> 94
A5: A — relevantan | B5: =COUNTIFS(Uzorak_100!$L$5:$L$104,"A",Uzorak_100!$N$5:$N$104,"da") -> 57
A6: B — graničan | B6: =COUNTIFS(Uzorak_100!$L$5:$L$104,"B",Uzorak_100!$N$5:$N$104,"da") -> 29
A7: C — nerelevantan | B7: =COUNTIFS(Uzorak_100!$L$5:$L$104,"C",Uzorak_100!$N$5:$N$104,"da") -> 8
A8: P(A) stroga preciznost | B8: =IF(B4>0,B5/B4,"") -> 0.60638298
A9: P(A ili B) šira preciznost | B9: =IF(B4>0,(B5+B6)/B4,"") -> 0.91489362
A10: Wilson 95 % donja, P(A) | B10: =IF(B4>0,((B8+1.96^2/(2*B4))-1.96*SQRT(B8*(1-B8)/B4+1.96^2/(4*B4^2)))/(1+1.96^2/B4),"") -> 0.5053094
A11: Wilson 95 % gornja, P(A) | B11: =IF(B4>0,((B8+1.96^2/(2*B4))+1.96*SQRT(B8*(1-B8)/B4+1.96^2/(4*B4^2)))/(1+1.96^2/B4),"") -> 0.69910263
A12: Wilson 95 % donja, P(A∪B) | B12: =IF(B4>0,((B9+1.96^2/(2*B4))-1.96*SQRT(B9*(1-B9)/B4+1.96^2/(4*B4^2)))/(1+1.96^2/B4),"") -> 0.84096188
A13: Wilson 95 % gornja, P(A∪B) | B13: =IF(B4>0,((B9+1.96^2/(2*B4))+1.96*SQRT(B9*(1-B9)/B4+1.96^2/(4*B4^2)))/(1+1.96^2/B4),"") -> 0.95624504
A15: Uzorak B (2005.–2015.; od 50 sirovih zapisa oni u čistom upitu)
A16: n (ocijenjeno) | B16: =COUNTIFS(Uzorak_50_rano!$L$5:$L$54,"A",Uzorak_50_rano!$N$5:$N$54,"da")+COUNTIFS(Uzorak_50_rano!$L$5:$L$54,"B",Uzorak_50_rano!$N$5:$N$54,"da")+COUNTIFS(Uzorak_50_rano!$L$5:$L$54,"C",Uzorak_50_rano!$N$5:$N$54,"da") -> 35
A17: A — relevantan | B17: =COUNTIFS(Uzorak_50_rano!$L$5:$L$54,"A",Uzorak_50_rano!$N$5:$N$54,"da") -> 13
A18: B — graničan | B18: =COUNTIFS(Uzorak_50_rano!$L$5:$L$54,"B",Uzorak_50_rano!$N$5:$N$54,"da") -> 12
A19: C — nerelevantan | B19: =COUNTIFS(Uzorak_50_rano!$L$5:$L$54,"C",Uzorak_50_rano!$N$5:$N$54,"da") -> 10
A20: P(A) stroga preciznost | B20: =IF(B16>0,B17/B16,"") -> 0.37142857
A21: P(A ili B) šira preciznost | B21: =IF(B16>0,(B17+B18)/B16,"") -> 0.71428571
A22: Wilson 95 % donja, P(A) | B22: =IF(B16>0,((B20+1.96^2/(2*B16))-1.96*SQRT(B20*(1-B20)/B16+1.96^2/(4*B16^2)))/(1+1.96^2/B16),"") -> 0.23165607
A23: Wilson 95 % gornja, P(A) | B23: =IF(B16>0,((B20+1.96^2/(2*B16))+1.96*SQRT(B20*(1-B20)/B16+1.96^2/(4*B16^2)))/(1+1.96^2/B16),"") -> 0.5366336
A24: Wilson 95 % donja, P(A∪B) | B24: =IF(B16>0,((B21+1.96^2/(2*B16))-1.96*SQRT(B21*(1-B21)/B16+1.96^2/(4*B16^2)))/(1+1.96^2/B16),"") -> 0.54944752
A25: Wilson 95 % gornja, P(A∪B) | B25: =IF(B16>0,((B21+1.96^2/(2*B16))+1.96*SQRT(B21*(1-B21)/B16+1.96^2/(4*B16^2)))/(1+1.96^2/B16),"") -> 0.83673637
A27: Razlika P(A): uzorak B (rano) − uzorak A (cijelo razdoblje)
A28: razlika udjela | B28: =B20-B8 -> -0.23495441
A29: z (dvoproporcijski test, združeni p) | B29: =IF(AND(B4>0,B16>0),(B20-B8)/SQRT(((B5+B17)/(B4+B16))*(1-(B5+B17)/(B4+B16))*(1/B4+1/B16)),"") -> -2.3817785
A30: p (dvostrano) | B30: =IF(B29="","",2*(1-NORMSDIST(ABS(B29)))) -> 0.017229256
A31: Tumačenje: p < 0,05 → preciznost je u ranom razdoblju bila niža (više generičkih UAV inženjerskih radova koji poljoprivredu samo spominju); strogo poljoprivredna produkcija stoga raste još brže nego serija upita, a apsolutni brojevi su precijenjeni.
A33: Napomena: formule se odnose na stupac L (KONAČNA OCJENA) oba lista; prazne ćelije se ne broje.

Sheet Uzorak_100
A1: Uzorak A: 100 slučajnih zapisa sirovog upita, 2005.–2025. (seed 20260828)
A2: Žuti stupac = KONAČNA OCJENA (A/B/C), popunite ili potvrdite; prijedlog (AI) je samo pomoć.
A4: # | B4: Godina | C4: Naslov | D4: Časopis / izvor | E4: OpenAlex tema | F4: OpenAlex ID (poveznica) | G4: DOI | H4: UAV pojam | I4: Sažetak (skraćen) | J4: Prijedlog (AI) | K4: Obrazloženje prijedloga | L4: KONAČNA OCJENA | M4: Napomena ocjenjivača | N4: U čistom upitu (da/ne)
A5: 1 | B5: 2024 | C5: Research on a UAV spray system combined with grid atomized droplets | D5: Frontiers in Plant Science | E5: Plant Surface Properties and Treatments | F5: https://openalex.org/W4390541202 | G5: https://doi.org/10.3389/fpls.2023.1286332 | H5: uav, uavs | I5: Backgrounds: UAVs for crop protection hold significant potential for application in mountainous orchard areas in China. However, certain issues pertaining to UAV spraying need to be addressed for further technological advancement, aimed at enhancing crop protection efficiency and reducing pesticide usage. These challenges include the potential for droplet drift, limited capacity for pesticide solution. Consequently, efforts are required to overcome these limitations and optimize UAV spraying technology. Methods: In order to balance high deposition and low drift in plant protection UAV spraying, this study proposes a plant protection UAV spraying method. In order to study the operational effe… | J5: A | K5: UAV sustav za prskanje, zaštita usjeva | L5: A | N5: da
A6: 2 | B6: 2025 | C6: Evolution of Deep Learning Approaches in UAV-Based Crop Leaf Disease Detection: A Web of Science Review | D6: Applied Sciences | E6: Smart Agriculture and AI | F6: https://openalex.org/W4414888839 | G6: https://doi.org/10.3390/app151910778 | H6: drone, uav, uavs, unmanned aerial | I6: The integration of unmanned aerial vehicles (UAVs) and deep learning (DL) has significantly advanced crop disease detection by enabling scalable, high-resolution, and near real-time monitoring within precision agriculture. This systematic review analyzes peer-reviewed literature indexed in the Web of Science Core Collection as articles or proceeding papers through 2024. The main selection criterion was combining “unmanned aerial vehicle*” OR “UAV” OR “drone” with “deep learning”, “agriculture” and “leaf disease” OR “crop disease”. Results show a marked surge in publications after 2019, with China, the United States, and India leading research contributions. Multirotor UAVs equipped with RGB … | J6: A | K6: Pregled: detekcija bolesti lišća usjeva UAV-om | L6: A | N6: da
A7: 3 | B7: 2024 | C7: An assessment of fertilizer spraying drones based on hesitancy fuzzy similarity measures for sustainable green development | D7: AIP Advances | E7: Multi-Criteria Decision Making | F7: https://openalex.org/W4391037627 | G7: https://doi.org/10.1063/5.0177649 | H7: drones | I7: This research proposes a new similarity measure on hesitancy fuzzy graphs. The similarity measures are crucial concepts to explore the closeness between fuzzy graphs. The available imprecise and inconsistent data were more effectively handled by fuzzy similarity measures and intuitionistic fuzzy similarity measures. With time in decision-making theory, a complex frame of the background that occurs cannot be specified entirely by these fuzzy graphs but generalized fuzzy graphs like the hesitancy fuzzy graph can handle such a situation efficiently. The applicability of Hesitancy Fuzzy Graph (HFG) attracted the researchers to generalize ranking order based on the working procedures I, II of Xu’… | J7: A | K7: Ocjena dronova za prskanje gnojiva | L7: A | N7: da
A8: 4 | B8: 2020 | C8: Estimation of Corn Leaf Area Index and Ground Cover With Vegetation Indices as a Result of Irrigation Dose | D8: Journal of Agricultural Science | E8: Leaf Properties and Growth Measurement | F8: https://openalex.org/W3104898804 | G8: https://doi.org/10.5539/jas.v12n12p234 | H8: drone, drones, unmanned aerial | I8: New technologies have been implemented in the agricultural sector to improve crop production and resource management including irrigation water. A three-year long project was conducted to determine whether vegetation indices (VIs) could be used to estimate the leaf area index (LAI) as well as the soil cover fraction (fc) at different crop growth stages in order to use these parameters in a future study concerning irrigation through drones. A low cost unmanned aerial vehicle (drone) and a multispectral camera were used to calculate different VIs of corn (Zea mays). The irrigation scheduling based on the FAO Penman-Monteith equation and the drip irrigation method were used. Three treatments we… | J8: A | K8: LAI kukuruza dronom, navodnjavanje | L8: A | N8: da
A9: 5 | B9: 2024 | C9: CADASTRAL WORKS OF AGRICULTURAL LAND IN THE REGION | D9: Moscow Economic Journal | E9: Regional Socio-Economic Development Trends | F9: https://openalex.org/W4405860565 | G9: https://doi.org/10.55186/2413046x_2024_9_12_469 | H9: uavs | I9: The article provides an analysis of cadastral works on agricultural lands in the region. For the purpose of the study, the data of agricultural lands, including municipal areas, are considered. An integrated approach and cadastral works using UAVs are considered. Based on the considered approaches, estimates of the effectiveness of cadastral works using UAVs are made. Methodologically, the scientific work is based on an analysis of the current state of cadastral works of agricultural lands, the dynamics of changes and an assessment of the state of cadastral works, a description of approaches to accelerating processes, including the economic costs of agriculture and an assessment of state sup… | J9: B | K9: Katastarski radovi na poljoprivrednom zemljištu UAV-om (izmjera) | L9: B | N9: da
A10: 6 | B10: 2017 | C10: A BIRD'S-EYE VIEW OF PROTO-TEWA SUBSISTENCE AGRICULTURE: MAKING THE CASE FOR FLOODPLAIN FARMING IN THE OHKAY OWINGEH HOMELAND, NEW MEXICO | D10: American Antiquity | E10: Archaeology and ancient environmental studies | F10: https://openalex.org/W2610778016 | G10: https://doi.org/10.1017/aaq.2017.3 | H10: uav, unmanned aerial | I10: Previous research on agriculture in the American Southwest focuses overwhelmingly on archaeological survey methods to discern surface agricultural features, which, in combination with climatological, geological, and geographical variables, are used to create models about agricultural productivity in the past. However, with few exceptions, the role of floodplain irrigation and floodwater farming in ancestral Pueblo agriculture is generally downplayed in scholarly discourse. Using a variety of methods, including Unmanned Aerial Vehicles (UAV), satellite imagery, pedestrian survey, and supervised classification of remotely sensed imagery, we examine this issue through a consideration of how anc… | J10: B | K10: Arheologija, UAV kao jedna od metoda | L10: B | N10: da
A11: 7 | B11: 2025 | C11: Connectivity-aware UAV mobility in cellular networks: DRL path planning and predictive handover | D11: Ad Hoc Networks | E11: UAV Applications and Optimization | F11: https://openalex.org/W4413905115 | G11: https://doi.org/10.1016/j.adhoc.2025.103999 | H11: uav | I11: (sažetak nije dostupan — otvoriti poveznicu) | J11: B | K11: UAV u mobilnim mrežama | L11: B | N11: da
A12: 8 | B12: 2019 | C12: Combination of wavelet transform and singular value decomposition-based contrast enhancement technique for target detection in UAV reconnaissance thermal images | D12: Journal of Modern Optics | E12: Advanced Image Fusion Techniques | F12: https://openalex.org/W2907362082 | G12: https://doi.org/10.1080/09500340.2018.1559949 | H12: uav, unmanned aerial | I12: In Aerial surveillance, thermal images acquired by unmanned aerial vehicle (UAV) are greatly affected due to various external interferences, which results in a low contrast image. Widely used conventional contrast enhancement methods such as histogram equalization and dynamic range partitioning techniques suffer from severe brightness changes and reduced sharpness, which in turn fail to preserve the edge details of the image. Thus for efficient target detection, it is essential to develop effective thermal infrared image contrast and edge enhancement technique. In this paper, wavelet transform (WT) and singular value decomposition (SVD)-based image enhancement technique is attempted for the … | J12: B | K12: Vojno izviđanje, termalne UAV snimke | L12: B | N12: da
A13: 9 | B13: 2025 | C13: Photosynthetic and Canopy Trait Characterization in Soybean (Glycine max L.) Using Chlorophyll Fluorescence and UAV Imaging | D13: Agriculture | E13: Remote Sensing in Agriculture | F13: https://openalex.org/W7114927957 | G13: https://doi.org/10.3390/agriculture15242576 | H13: uav | I13: Photosynthesis (PS) is the cornerstone of crop productivity, directly influencing yield potential. Photosynthesis remains an underexploited target in soybean breeding, partly because field-based photosynthetic traits are difficult to measure at scale. Also, it is unclear which reproductive stage(s) provide the most informative physiological signals for yield. Few studies have evaluated soybean PS in elite germplasm under field conditions, and the integration of chlorophyll fluorescence (CF) with UAV imaging for PS traits remains largely unexplored. This study evaluated genotypic variation in photosynthetic and canopy traits among elite soybean germplasm across environments and developmental … | J13: A | K13: Soja, fluorescencija klorofila i UAV snimanje | L13: A | N13: da
A14: 10 | B14: 2022 | C14: Using Visible and Thermal Images by an Unmanned Aerial Vehicle to Monitor the Plant Water Status, Canopy Growth and Yield of Olive Trees (cvs. Frantoio and Leccino) under Different Irrigation Regimes | D14: Agronomy | E14: Remote Sensing in Agriculture | F14: https://openalex.org/W4291414394 | G14: https://doi.org/10.3390/agronomy12081904 | H14: uav, unmanned aerial | I14: An efficient management of water relies on the correct estimation of tree water requirements and the accurate monitoring of tree water status and canopy growth. This study aims to test the suitability of visible and thermal images acquired by an unmanned aerial vehicle (UAV) for monitoring tree water status and canopy growth in an irrigation experiment. We used mature olive trees of two cultivars subjected to full irrigation, deficit irrigation (41–44% of full irrigation), or rainfed conditions. Deficit irrigation had limited or no effect on fruit and oil yield. There was a significant relationship between the remotely sensed crop water stress index derived from thermal images and the stem w… | J14: A | K14: Masline, vodni status UAV-om | L14: A | N14: da
A15: 11 | B15: 2023 | C15: Development of Methods for Top-Down Methane Emission Measurements of Oil and Gas Facilities in an Offshore Environment Using a Miniature Methane Spectrometer and Long-Endurance Uncrewed Aerial System | D15: SPE Production & Operations | E15: Atmospheric and Environmental Gas Dynamics | F15: https://openalex.org/W4385628948 | G15: https://doi.org/10.2118/206181-pa | H15: uav | I15: Summary With atmospheric methane concentrations rising and spurring increased social concern, there is a renewed focus in the oil and gas industry on methane emission monitoring and control. In 2019, a methane emission survey at a bp asset west of Shetland was conducted using a closed-cavity methane spectrometer mounted onboard a long-endurance fixed-wing uncrewed aerial vehicle (UAV). This flight represents the first methane emissions survey of an offshore facility with a miniature methane spectrometer onboard a UAV with subsequent flights performed. A small laser spectrometer was modified from an open-cavity system to a closed-cavity onboard the aircraft and yielded in-flight detection lim… | J15: B | K15: Emisije metana s platforme, UAV (nije poljoprivreda) | L15: B | N15: da
A16: 12 | B16: 2024 | C16: Quantifying lower crop radiation availability in strip intercropping systems via UAV-derived canopy structural models | D16: Computers and Electronics in Agriculture | E16: Greenhouse Technology and Climate Control | F16: https://openalex.org/W4405198954 | G16: https://doi.org/10.1016/j.compag.2024.109691 | H16: uav | I16: • UAV-derived canopy model quantified radiation availability of intercropped soybean. • Shadow fraction method was developed to calculate direct, diffuse radiation and RUE. • RUE of intercropped soybean was higher than that in monoculture. • Fraction of diffuse in intercropping was slightly lower than that in monoculture. • Other factors leading to the higher RUE of soybean in intercropping systems. Shading is an unavoidable phenomenon in strip intercropping systems for lower crops, which affects the amount and component of solar radiation, and thus the radiation use efficiency (RUE). The higher crop is usually treated as a homogeneous block instead of the actual canopy structure to calculat… | J16: A | K16: Međuusjevi, UAV model krošnje | L16: A | N16: da
... A51: 47 | B51: 2020 | C51: Analysis of Plant Height Changes of Lodged Maize Using UAV-LiDAR Data | D51: Agriculture | E51: Crop Yield and Soil Fertility | F51: https://openalex.org/W3023299871 | G51: https://doi.org/10.3390/agriculture10050146 | H51: uav, unmanned aerial | I51: Lodging stress seriously affects the yield, quality, and mechanical harvesting of maize, and is a major natural disaster causing maize yield reduction. The aim of this study was to obtain light detection and ranging (LiDAR) data of lodged maize using an unmanned aerial vehicle (UAV) equipped with a RIEGL VUX-1UAV sensor to analyze changes in the vertical structure of maize plants with different degrees of lodging, and thus to use plant height to quantitatively study maize lodging. Based on the UAV-LiDAR data, the height of the maize canopy was retrieved using a canopy height model to determine the height of the lodged maize canopy at different times. The profiles were analyzed to assess chan… | J51: A | K51: Polegli kukuruz, UAV LiDAR | L51: A | N51: da
A52: 48 | B52: 2013 | C52: A comparison of survey methods for monitoring crop damage by wild boar (Sus scrofa) | E52: Wildlife Ecology and Conservation | F52: https://openalex.org/W1023572571 | H52: drone | I52: Abstract This paper compares three different survey methods for monitoring wild boar (Sus scrofa) damage to agricultural crops on the island of Morko, Sweden. The first method investigated was also the most conventional and involved walking through the fields on foot to locate and measure patches of wild boar damage. This method was compared to a second that involved the use of a remotely controlled aerial drone which took digital photographs of the fields. These photographs were then analyzed and observed damaged areas were recorded. The third method considered the theory that most wild boar damage to crops occurs on the edge of the fields, in order to determine if a relationship exists bet… | J52: A | K52: Šteta divlje svinje na usjevima, dron | L52: A | N52: da
A53: 49 | B53: 2022 | C53: Impact of Drone Spraying of Nutrients on Growth and Yield of Maize Crop | D53: International Journal of Environment and Climate Change | E53: Plant Surface Properties and Treatments | F53: https://openalex.org/W4285095462 | G53: https://doi.org/10.9734/ijecc/2022/v12i1130972 | H53: drone, drones, unmanned aerial | I53: This study aimed at utilizing unmanned aerial vehicle in place of a conventional hand sprayer for the smart delivery of agricultural inputs especially crop nutrients. A field experiment was conducted in the farms of Agricultural Research Station, Bhavanisagar, Tamil Nadu Agricultural University. There were nine treatments which were replicated thrice in a randomized block design. The treatments include NPK 19:19:19 along with liquid micronutrient, humic acid, and TNAU Maize maxim at two intervals viz., 50% Tasselling, and Cob filling stage. These nutrients were applied as foliar spray through battery operated and fuel operated drones and were compared with knapsack hand sprayer. Biometric ob… | J53: A | K53: Prskanje hraniva dronom, kukuruz | L53: A | N53: da
A54: 50 | B54: 2021 | C54: Monitoring of peanut leaves chlorophyll content based on drone-based multispectral image feature extraction | D54: Computers and Electronics in Agriculture | E54: Remote Sensing and Land Use | F54: https://openalex.org/W3180151162 | G54: https://doi.org/10.1016/j.compag.2021.106292 | H54: drone | I54: (sažetak nije dostupan — otvoriti poveznicu) | J54: A | K54: Klorofil kikirikija, dron | L54: A | N54: da
A55: 51 | B55: 2024 | C55: Use of unmanned aerial vehicle-derived multi-spectral data for the early detection of multi-temporal maize leaf equivalent water thickness and fuel moisture content for the improved resilience of smallholder maize farming | D55: Journal of Applied Remote Sensing | E55: Crop Yield and Soil Fertility | F55: https://openalex.org/W4392586286 | G55: https://doi.org/10.1117/1.jrs.18.014520 | H55: uav, uavs, unmanned aerial | I55: Maize water stress from rainfall variability is a key challenge in producing rain-fed maize farming, especially in water-scarce regions, such as southern Africa. Hence, quantifying maize foliar water content variations throughout the phenological stages is valuable in detecting smallholder maize moisture stress and supporting agricultural decision-making. The emergence of unmanned aerial vehicles (UAVs) equipped with multispectral sensors offers a unique opportunity for robust and rapid monitoring of maize foliar water content and stress. The combination of near-real-time spatially explicit information acquired using UAV imagery with physiological indicators, such as equivalent water thickne… | J55: A | K55: Kukuruz, rana detekcija, UAV | L55: A | N55: da
A56: 52 | B56: 2022 | C56: Improving Estimation of Winter Wheat Nitrogen Status Using Random Forest by Integrating Multi-Source Data Across Different Agro-Ecological Zones | D56: Frontiers in Plant Science | E56: Remote Sensing in Agriculture | F56: https://openalex.org/W4281656810 | G56: https://doi.org/10.3389/fpls.2022.890892 | H56: unmanned aerial | I56: Timely and accurate estimation of plant nitrogen (N) status is crucial to the successful implementation of precision N management. It has been a great challenge to non-destructively estimate plant N status across different agro-ecological zones (AZs). The objective of this study was to use random forest regression (RFR) models together with multi-source data to improve the estimation of winter wheat ( Triticum aestivum L.) N status across two AZs. Fifteen site-year plot and farmers' field experiments involving different N rates and 19 cultivars were conducted in two AZs from 2015 to 2020. The results indicated that RFR models integrating climatic and management factors with vegetation index … | J56: A | K56: Dušik u pšenici, UAV + satelit | L56: A | N56: da
A57: 53 | B57: 2025 | C57: Dynamics of carbon stock and normalized difference vegetation index as indicators of oil palm (Elaeis guineensis Jacq.) productivity in peat ecosystem with compound NPK fertilizer application | D57: Journal of Ecological Engineering | E57: Oil Palm Production and Sustainability | F57: https://openalex.org/W4411542673 | G57: https://doi.org/10.12911/22998993/205107 | H57: uav | I57: This study investigated the dynamics of carbon stock and normalized difference vegetation index (NDVI) as indicators of oil palm (Elaeis guineensis Jacq.) productivity in peat ecosystems under varying applications of compound NPK fertilizer.Research was conducted in Benteng Hulu Village, Mempura District, Siak Regency, Riau Province, Indonesia, from March 2023 to April 2024 using mature oil palm plants (10-12 years old) grown on different peat depths.A nested plot design was employed with three peat depth categories (shallow: 1-2 m, moderate: 2-3 m, and deep: > 3 m) as main plots and five Compound NPK fertilizer treatments (T0: control, T1: 75%, T2: 100%, T3: 125%, and T4: 150% of recommende… | J57: A | K57: Uljna palma, UAV NDVI | L57: A | N57: da
A58: 54 | B58: 2012 | C58: Near-optimal coverage trajectories for image mosaicing using a mini quad-rotor over irregular-shaped fields | D58: Precision Agriculture | E58: Robotic Path Planning Algorithms | F58: https://openalex.org/W2133808775 | G58: https://doi.org/10.1007/s11119-012-9287-0 | H58: (nije u naslovu/sažetku) | I58: (sažetak nije dostupan — otvoriti poveznicu) | J58: B | K58: Putanje mini kvadrotora za mozaik (generičko) | L58: B | N58: da
A59: 55 | B59: 2015 | C59: GENETIC AND EVOLUTIONARY ANALYSIS OF PLANT REPLICATION PROTEIN A 1 (RPA1) | D59: University of New Hampshire Scholars Repository (University of New Hampshire at Manchester) | E59: DNA Repair Mechanisms | F59: https://openalex.org/W1165425494 | H59: (nije u naslovu/sažetku) | I59: Challenging human health issues include treatments for genetic diseases and providing improved agricultural crop output to feed the growing world population. The project described here, which focuses on how cells respond to chromosomal (genomic) damage, has significant implications in each example. In humans, accumulation of DNA damage induced mutations can result in genetic diseases such as cancer, and in plants can similarly result in genome instability, reducing productivity. Organisms from human to plants have conserved mechanisms to counteract DNA damage. However, detailed genetic and biochemical information on plant DNA repair systems is still limited. The goal of this dissertation was… | J59: C | K59: RPA1 protein | L59: C | N59: da
A60: 56 | B60: 2023 | C60: Small and Oriented Wheat Spike Detection at the Filling and Maturity Stages Based on WheatNet | D60: Plant Phenomics | E60: Smart Agriculture and AI | F60: https://openalex.org/W4387653126 | G60: https://doi.org/10.34133/plantphenomics.0109 | H60: drone | I60: Accurate wheat spike detection is crucial in wheat field phenotyping for precision farming. Advances in artificial intelligence have enabled deep learning models to improve the accuracy of detecting wheat spikes. However, wheat growth is a dynamic process characterized by important changes in the color feature of wheat spikes and the background. Existing models for wheat spike detection are typically designed for a specific growth stage. Their adaptability to other growth stages or field scenes is limited. Such models cannot detect wheat spikes accurately caused by the difference in color, size, and morphological features between growth stages. This paper proposes WheatNet to detect small an… | J60: A | K60: Klasovi pšenice u dronskim snimkama | L60: A | N60: da
A61: 57 | B61: 2017 | C61: イネの形質と UAV リモートセンシングデータから計算されたカラー指標との比較 | D61: CGSPace A Repository of Agricultural Research Outputs (Consultative Group for International Agricultural Research) | E61: Remote Sensing in Agriculture | F61: https://openalex.org/W2592285551 | G61: https://doi.org/10.11450/seitaikogaku.29.11 | H61: uav, unmanned aerial | I61: Remote sensing technology for monitoring plant trains has a huge potential to accelerate breeding process. In this paper, we have studied on remote sensing of using an unmanned aerial vehicle (UAV) system for plant traits phenotyping in rice. The images of rice canopy were taken by a RGB camera from the UAV at three growing stages; Vegetative (VG), Flowering (FW) and Grain filling (GF). Typical color indices (r, g, b, INT, VIG, L*, a*, b*, H) were calculated by image processing. Single regression analysis was conducted between rice plant traits (leaf area index (LAI), grain yield, above ground biomass, plant height, panicle length, grain filling rate, tiller number) and color indices. The in… | J61: A | K61: Riža, UAV (japanski) | L61: A | N61: da
A62: 58 | B62: 2022 | C62: Multisite and Multitemporal Grassland Yield Estimation Using UAV-Borne Hyperspectral Data | D62: Remote Sensing | E62: Remote Sensing in Agriculture | F62: https://openalex.org/W4224659716 | G62: https://doi.org/10.3390/rs14092068 | H62: uav, uavs, unmanned aerial | I62: Grassland ecosystems can be hotspots of biodiversity and act as carbon sinks while at the same time providing the basis of forage production for ruminants in dairy and meat production. Annual grassland dry matter yield (DMY) is one of the most important agronomic parameters reflecting differences in usage intensity such as number of harvests and fertilization. Current methods for grassland DMY estimation are labor-intensive and prone to error due to small sample size. With the advent of unmanned aerial vehicles (UAVs) and miniaturized hyperspectral sensors, a novel tool for remote sensing of grassland with high spatial, temporal and radiometric resolution and coverage is available. The prese… | J62: A | K62: Prinos travnjaka, UAV hiperspektralno | L62: A | N62: da
A63: 59 | B63: 2025 | C63: Transforming Agriculture through AI and Drone technique | D63: Agricultural Engineering Today | E63: Smart Agriculture and AI | F63: https://openalex.org/W4410465179 | G63: https://doi.org/10.52151/aet2022464.1602 | H63: drone | I63: India is one of the major agricultural players in the world, 58% of its population is involved in agriculturerelated work and depends on it as a primary source of income. For decades, Agriculture has been a key focus of economists for the simple reason that it contributes to over 18% of the Indian GDP and provides livelihood to 700 million people in India. Over the course of time, India has achieved significant milestones in terms of global ranking in the production of food grains, milk and horticulture. However, the challenges of the Indian agriculture ecosystem remain the same as before because of fragmentation and inefficiency. Despite this, new innovations and technological intervention … | J63: A | K63: Pregled: AI i dronovi u poljoprivredi | L63: A | N63: da
A64: 60 | B64: 2025 | C64: Crop classification with UAV multispectral remote sensing, employing an enhanced ResNet50 residual network | D64: PLoS ONE | E64: Remote Sensing in Agriculture | F64: https://openalex.org/W7117623597 | G64: https://doi.org/10.1371/journal.pone.0339644 | H64: uav | I64: The ResNet50 residual network model is characterized by its rapid training speed and high classification accuracy, demonstrating significant advantages in extracting and classifying crop features. However, the correlation and redundant information among different spectral bands in multispectral data can negatively affect classification accuracy. Additionally, the ResNet50 model does not meet the requirements for training with multi-band data, and its classification accuracy in small-scale, high-precision scenarios needs further improvement. This study focuses on flue-cured tobacco and maize to address these challenges, identifying the optimal classification band combination. Enhancements to … | J64: A | K64: Klasifikacija usjeva UAV-om | L64: A | N64: da
A65: 61 | B65: 2023 | C65: Heterogeneity Assessment of Kenaf Breeding Field through Spatial Dependence Analysis on Crop Growth Status Map Derived by Unmanned Aerial Vehicle | D65: Plants | E65: Remote Sensing in Agriculture | F65: https://openalex.org/W4365514608 | G65: https://doi.org/10.3390/plants12081638 | H65: uav, unmanned aerial | I65: The investigation of quantitative phenotypic traits resulting from the interaction between targeted genotypic traits and environmental factors is essential for breeding selection. Therefore, plot-wise controlled environmental factors must be invariable for accurate identification of phenotypes. However, the assumption of homogeneous variables within the open-field is not always accepted, and requires a spatial dependence analysis to determine whether site-specific environmental factors exist. In this study, spatial dependence within the kenaf breeding field was assessed in a geo-tagged height map derived from an unmanned aerial vehicle (UAV). Local indicators of spatial autocorrelation (LISA… | J65: A | K65: Kenaf, oplemenjivanje, UAV | L65: A | N65: da
A66: 62 | B66: 2017 | C66: Spatio-temporal monitoring of cotton cultivation using ground-based and airborne multispectral sensors in GIS environment | D66: Environmental Monitoring and Assessment | E66: Remote Sensing in Agriculture | F66: https://openalex.org/W2621510117 | G66: https://doi.org/10.1007/s10661-017-6042-z | H66: (nije u naslovu/sažetku) | I66: (sažetak nije dostupan — otvoriti poveznicu) | J66: C | K66: Nema UAV pojma (airborne senzori) | L66: C | N66: da
A67: 63 | B67: 2025 | C67: Gradient-Based Optimization of Terrestrial Cellular Networks for Aerial Highways | D67: IEEE Transactions on Vehicular Technology | E67: UAV Applications and Optimization | F67: https://openalex.org/W4415743546 | G67: https://doi.org/10.1109/tvt.2025.3627332 | H67: uav, uavs, unmanned aerial | I67: Unmanned aerial vehicles (UAVs), owing to their ability to navigate 3D space and encounter line of sight (LoS) conditions, often experience high channel gains across multiple cells. This phenomena results in comparable signal power from various neighboring cells, causing significant interference and reduced signal-to-interference-plus-noise ratio (SINR), which complicates their integration into terrestrial networks. In this paper, we investigate how prior knowledge of planned aerial highways (AHs) can be leveraged by network operators to efficiently optimize their infrastructures for seamless UAV connectivity. In particular, we propose a gradient-based optimization algorithm to adjust the ve… | J67: B | K67: Mobilne mreže za UAV koridore | L67: B | N67: da
A68: 64 | B68: 2024 | C68: APW: An ensemble model for efficient wheat spike counting in unmanned aerial vehicle images | D68: Computers and Electronics in Agriculture | E68: Smart Agriculture and AI | F68: https://openalex.org/W4400144873 | G68: https://doi.org/10.1016/j.compag.2024.109204 | H68: unmanned aerial | I68: (sažetak nije dostupan — otvoriti poveznicu) | J68: A | K68: Brojanje klasova pšenice UAV | L68: A | N68: da
A69: 65 | B69: 2023 | C69: Building responsive and resilient supply chains: Lessons from the COVID ‐19 disruption | D69: Journal of Operations Management | E69: Supply Chain Resilience and Risk Management | F69: https://openalex.org/W4365518480 | G69: https://doi.org/10.1002/joom.1250 | H69: drone | I69: Since the first case was identified, COVID-19 has spread to more than 200 countries. As of October 25, 2022, it had resulted in over 6 million deaths and 600 million confirmed cases. The rapid widespread of COVID-19 led to large-scale disruptions with major supply and demand shocks in supply chains, causing significant negative impacts on the global economy. The World Bank reported that the world GDP growth rate for 2020 was −3.27%, indicating the worst recession since 1961. First, the initial epidemic-control efforts blocked the flows of raw materials across the world, and limited labor movements by imposing temporary travel restrictions. As a result, many firms struggled with supply disrup… | J69: C | K69: Opskrbni lanci; tvrtka Terra Drone | L69: C | N69: ne
A70: 66 | B70: 2017 | C70: Influence of nitrogen deficiency or excess on a root system structure of maize and triticale seedlings grown under low and high soil density | D70: Journal of Agronomy and Crop Science | E70: Plant nutrient uptake and metabolism | F70: https://openalex.org/W2767496368 | G70: https://doi.org/10.1111/jac.12248 | H70: (nije u naslovu/sažetku) | I70: Abstract Responses of maize and triticale seedlings, differing in the susceptibility to soil density stress, and grown under low (LD) or high (HD) soil density and poor (PN), high (HN) or control (CN) nitrogen content in soil were investigated in relation to changes in physiological parameters—dry matter of shoot (S), root (R), shoot to root ratio (S/R), relative growth ratio of shoot and root (RGR), chlorophyll content (SPAD), total roots number and length (TRN, TRL), root penetration ability (RPA) and ratio of deep rooting (RDR). The seedlings grown under high soil density (HD) and control N‐soil content (CN) in comparison with LD and CN treatments showed a decrease in all measured paramet… | J70: C | K70: Nema UAV pojma (korijen kukuruza) | L70: C | N70: da
A71: 67 | B71: 2012 | C71: Mapping radiation interception in row-structured orchards using 3D simulation and high-resolution airborne imagery acquired from a UAV | D71: Precision Agriculture | E71: Remote Sensing in Agriculture | F71: https://openalex.org/W2017014841 | G71: https://doi.org/10.1007/s11119-012-9263-8 | H71: uav | I71: (sažetak nije dostupan — otvoriti poveznicu) | J71: A | K71: Voćnjaci, UAV snimke | L71: A | N71: da
... A79: 75 | B79: 2025 | C79: From pixels to peaks: integrating LiDAR and RGB drone imagery to map mussel spat on intertidal rocky shores | D79: Estuarine Coastal and Shelf Science | E79: Remote Sensing and LiDAR Applications | F79: https://openalex.org/W4417537437 | G79: https://doi.org/10.1016/j.ecss.2025.109671 | H79: drone, uav, uavs, unmanned aerial | I79: Remote monitoring of the spatial cover of sessile intertidal species can provide important information for the conservation and management of commercial species. However, the use of high-resolution RGB imagery combined with topographic data acquired by Unmanned Aerial Vehicles (UAVs) to map rocky intertidal sessile invertebrates, particularly wild spat of Mytilus galloprovincialis , remains largely unexplored. Galicia (northwestern Spain) is the leading producer of farmed mussels in Europe, and most of mussel rafts are seeded with wild spat collected from intertidal rocks. Using a UAV equipped with an RGB camera and LiDAR sensor, we surveyed a rocky intertidal area in Galicia where mussel sp… | J79: B | K79: Dagnje na obali, dron (ekologija/akvakultura) | L79: B | N79: da
A80: 76 | B80: 2018 | C80: Enhanced Vineyard Descriptors combining UAV 2D and 3D Crop Models | E80: Smart Agriculture and AI | F80: https://openalex.org/W2884335044 | H80: uav | I80: (sažetak nije dostupan — otvoriti poveznicu) | J80: A | K80: Vinograd, UAV 2D/3D | L80: A | N80: da
A81: 77 | B81: 2025 | C81: Assessing the effectiveness of filtering algorithms and semantic segmentation for photogrammetric UAV-derived digital terrain models in urban and sloped environments | D81: Survey Review | E81: 3D Surveying and Cultural Heritage | F81: https://openalex.org/W4417055510 | G81: https://doi.org/10.1080/00396265.2025.2596381 | H81: uav | I81: This study evaluates the performance of rule-based (LAstools, CSF, ATIN) and AI-based (PointCNN, RandLA-Net, SQN, Random Forest) filtering algorithms for DTM derivation on two UAV photogrammetric datasets. Results show that algorithm performance mainly depends on terrain morphology. Particularly, at the flat urban site (Thammasat dataset), LAStools yielded the best RMSE of 0.94 m and a recall of 0.89. At the sloped terrain site (Cadastre dataset), CSF produced the best results RMSE 0.72 m and recall 0.90. Deep Learning approaches achieved recall values up to 0.94. Overall, LAStools performed best in flat terrain, whereas CSF produced optimal results in sloped areas. | J81: B | K81: UAV DTM u urbanim područjima | L81: B | N81: da
A82: 78 | B82: 2025 | C82: Iterative optimization annotation pipeline and ALSS-YOLO-Seg for efficient banana plantation segmentation in UAV imagery | D82: Frontiers in Plant Science | E82: Smart Agriculture and AI | F82: https://openalex.org/W4406132323 | G82: https://doi.org/10.3389/fpls.2024.1508549 | H82: uav, unmanned aerial | I82: Precise segmentation of unmanned aerial vehicle (UAV)-captured images plays a vital role in tasks such as crop yield estimation and plant health assessment in banana plantations. By identifying and classifying planted areas, crop areas can be calculated, which is indispensable for accurate yield predictions. However, segmenting banana plantation scenes requires a substantial amount of annotated data, and manual labeling of these images is both timeconsuming and labor-intensive, limiting the development of large-scale datasets. Furthermore, challenges such as changing target sizes, complex ground backgrounds, limited computational resources, and correct identification of crop categories make … | J82: A | K82: Plantaža banana, UAV | L82: A | N82: da
A83: 79 | B83: 2022 | C83: UAV-Supported Route Planning for UGVs in Semi-Deterministic Agricultural Environments | D83: Agronomy | E83: Robotic Path Planning Algorithms | F83: https://openalex.org/W4292258994 | G83: https://doi.org/10.3390/agronomy12081937 | H83: uav, unmanned aerial | I83: Automated agricultural operations must be planned and organized to reduce risk and failure potential while optimizing productivity and efficiency. However, the diversity of natural outdoor environments and the varied data types and volumes required to represent an agricultural setting comprise critical challenges for the deployment of fully automated agricultural operations. In this regard, this study develops an integrated system for enabling an unmanned aerial vehicle (UAV) supported route planning system for unmanned ground vehicles (UGVs) in the semi-structured environment of orchards. The research focus is on the underpinning planning system components (i.e., world representation or map… | J83: A | K83: UAV planiranje ruta za UGV u poljoprivredi | L83: A | N83: da
A84: 80 | B84: 2023 | C84: Emerging technologies revolutionising disease diagnosis and monitoring in aquatic animal health | D84: Reviews in Aquaculture | E84: Water Quality Monitoring Technologies | F84: https://openalex.org/W4388015873 | G84: https://doi.org/10.1111/raq.12870 | H84: drones | I84: Abstract In recent years, aquaculture has seen tremendous growth worldwide due to technological advancements, leading to research and development of various innovations. Aquaculture farmers prioritise early diagnosis for timely treatment to achieve better productive and economic performance. Aquatic animal health experts still employ traditional diagnostic methods using visual diagnosis, cell culture, media culture, histopathology and serology. However, the developments of technologies in aquamedicine, such as sequencing, biosensors and CRISPR, have enabled rapid disease detection within minutes. Furthermore, integrating sensors, drones, artificial intelligence and the internet in aquacultur… | J84: B | K84: Akvakultura, dronovi spomenuti | L84: B | N84: da
A85: 81 | B85: 2023 | C85: A Simple Analytical Model for THz Band Path Loss | D85: IEEE Communications Letters | E85: Millimeter-Wave Propagation and Modeling | F85: https://openalex.org/W4319990454 | G85: https://doi.org/10.1109/lcomm.2023.3241403 | H85: drone | I85: In this letter, we devise a frequency, distance, and altitude-dependent, analytical model for THz band path loss. This model is obtained from cascaded regression of transmittance data from Line-by-Line Radiative Transfer Model (LBLRTM) propagation analysis tool, considering altitudes from the sea-level to 1 km, distances from 1 m to 100 m and frequencies within 0.79-0.91 THz and 0.93-0.94 THz. The proposed approach yields high accuracy with respect to propagation data while providing a simple, closed-form expression to help the design of Terahertz (THz) band drone communications. | J85: B | K85: THz komunikacije dronova | L85: B | N85: da
A86: 82 | B86: 2017 | C86: Characteristics of UAV Aerial Images for Monitoring of Highland Kimchi Cabbage | D86: 한국토양비료학회지 | E86: Remote Sensing and Land Use | F86: https://openalex.org/W2768821646 | G86: https://doi.org/10.7745/kjssf.2017.50.3.162 | H86: uav, unmanned aerial | I86: Remote sensing can be used to provide information about the monitoring of crop growth condition. Recently Unmanned Aerial Vehicle (UAV) technology offers new opportunities for assessing crop growth condition using UAV imagery. The objective of this study was to assess weather UAV aerial images are suitable for the monitoring of highland Kimchi cabbage. This study was conducted using a fixed-wing UAV (Model : Ebee) with Cannon S110, IXUS/ELPH camera during farming season from 2015 to 2016 in the main production area of highland Kimchi cabbage, Anbandegi, Maebongsan, and Gwinemi. The Normalized Difference Vegetation Index (NDVI) by using UAV images was stable and suitable for monitoring of Kim… | J86: A | K86: Kupus, UAV snimke | L86: A | N86: da
A87: 83 | B87: 2025 | C87: EECH HEED an adaptive hybrid clustering protocol for energy efficient soil monitoring in heterogeneous wireless sensor networks | D87: Scientific Reports | E87: Energy Efficient Wireless Sensor Networks | F87: https://openalex.org/W4415041591 | G87: https://doi.org/10.1038/s41598-025-19480-y | H87: uav | I87: Wireless Sensor Networks (WSNs) play a pivotal role in precision agriculture, especially for real-time soil health monitoring. However, the limited energy capacity of sensor nodes poses a significant challenge to achieving prolonged network lifetime and consistent data transmission. Existing clustering protocols often struggle with inefficient cluster head (CH) selection, limited adaptability to heterogeneous environments, and excessive control overhead. To address these issues, this paper proposes EECH-HEED, a hybrid and energy-efficient clustering model designed for soil monitoring in heterogeneous WSNs. The proposed protocol utilizes a dual-zone architecture: Zone 1, located near the base… | J87: B | K87: WSN za tlo; UAV kao budući rad | L87: B | N87: da
A88: 84 | B88: 2025 | C88: From smallholder to commercial farming: the impact of termite mound levelling and spatial heterogeneity in mound morphology on soil organic carbon in Miombo woodlands, Central Africa | D88: Landscape Ecology | E88: Ecology and Vegetation Dynamics Studies | F88: https://openalex.org/W4409384098 | G88: https://doi.org/10.1007/s10980-025-02097-x | H88: uav, unmanned aerial | I88: Abstract Context The recent expansion of commercial agriculture in the Miombo woodlands of central Africa has led to widespread levelling of termite mounds. These mounds contain significantly lower soil organic carbon (SOC) than surrounding soils, and their levelling could largely reduce SOC content in the plough layer, which remains understudied. Objectives We aim to investigate the effects of mound levelling on SOC of the plough layer in a 1.5 km 2 plot used for commercial farming and quantify the contribution of pre-existing termite mounds to SOC variation in the levelled cropland. Methods Before and after levelling, we conducted unmanned aerial vehicle (UAV) surveys with structure-from-m… | J88: A | K88: Ravnanje termitnjaka, UAV snimanje oranica | L88: A | N88: da
A89: 85 | B89: 2024 | C89: Detection and monitoring wheat diseases using unmanned aerial vehicles (UAVs) | D89: Computers and Electronics in Agriculture | E89: Smart Agriculture and AI | F89: https://openalex.org/W4399715967 | G89: https://doi.org/10.1016/j.compag.2024.109158 | H89: uavs, unmanned aerial | I89: (sažetak nije dostupan — otvoriti poveznicu) | J89: A | K89: Bolesti pšenice UAV-om | L89: A | N89: da
A90: 86 | B90: 2025 | C90: Textural Characterization of Sugarcane Areas with Mucuna Aterrima Infestation Using Remotely Piloted Aircraft in the Eastern Brazilian Amazon | D90: Journal of the Indian Society of Remote Sensing | E90: African Botany and Ecology Studies | F90: https://openalex.org/W4415540653 | G90: https://doi.org/10.1007/s12524-025-02331-8 | H90: remotely piloted aircraft | I90: (sažetak nije dostupan — otvoriti poveznicu) | J90: A | K90: Šećerna trska, RPA snimke (pojam skraćen u naslovu) | L90: A | N90: da
A91: 87 | B91: 2025 | C91: Beyond the Fields: Building Smart Agricultural Infrastructure for Tomorrow | D91: Zenodo (CERN European Organization for Nuclear Research) | E91: Smart Agriculture and AI | F91: https://openalex.org/W7104373225 | G91: https://doi.org/10.5281/zenodo.17551816 | H91: drone, drones | I91: Introduction: A New Dawn in Agricultural Transformation Agriculture is no longer confined to manual labor and unpredictable outcomes—it is rapidly evolving into a technology-driven ecosystem. The modern farming landscape is witnessing a remarkable shift, where Crop Monitoring Systems and digital tools are redefining productivity, sustainability, and decision-making. Farmers today have access to data-driven insights, real-time updates, and automation technologies that simplify every step—from soil preparation to harvest. This integration of software and smart systems forms the foundation of tomorrow’s agricultural infrastructure, transforming farms into connected, intelligent hubs of innovati… | J91: B | K91: Pametna infrastruktura; dronovi spomenuti | L91: B | N91: da
A92: 88 | B92: 2023 | C92: A fast and efficient approach to estimate wild blueberry yield using machine learning with drone photography: Flight altitude, sampling method and model effects | D92: Computers and Electronics in Agriculture | E92: Berry genetics and cultivation research | F92: https://openalex.org/W4389844005 | G92: https://doi.org/10.1016/j.compag.2023.108543 | H92: drone | I92: (sažetak nije dostupan — otvoriti poveznicu) | J92: A | K92: Prinos borovnice, dron | L92: A | N92: da
... A94: 90 | B94: 2024 | C94: Use of different vegetation indices for the evaluation of the kinetics of the cherry tomato (Solanum lycopersicum var. cerasiforme) growth based on multispectral images by UAV | D94: Open Agriculture | E94: Remote Sensing in Agriculture | F94: https://openalex.org/W4402597053 | G94: https://doi.org/10.1515/opag-2022-0357 | H94: uav, unmanned aerial | I94: Abstract This study evaluated seven vegetation indices for the monitoring of a cherry tomato crop using an unmanned aerial vehicle with a multispectral camera that measures in the green, red, and near-infrared spectral bands. A photogrammetric flight plan was designed to capture the spectral images every 2 weeks in two agricultural parcels identified as Treatment 1 ( T 1 {T}_{1} ) and Treatment 2 ( T 2 {T}_{2} ). The corresponding orthophotographs were obtained using digital photogrammetry techniques. Subsequently, vegetation indices were calculated for these orthophotographs. The mean and standard deviation of these indices were extracted, and a statistical analysis was performed to compare… | J94: A | K94: Cherry rajčica, UAV indeksi | L94: A | N94: da
A95: 91 | B95: 2013 | C95: Consultancy Pattern among Agriculture Students at UAS, Bangalore (Karnataka) | E95: Agricultural Innovations and Practices | F95: https://openalex.org/W2278773080 | H95: uas | I95: A study was conducted at UAS, Bangalore (Karnataka) during 2009 to know the consultancy pattern among students for job placement. Data were collected from B.Sc (Agriculture) final year 120 students with the help of structured pre-tested interview schedule. The study revealed that majority of the students used mass media sources to a maximum extent followed by informal and formal sources. Among the mass media sources, most of the students used website followed by newspapers, television and journals. friends, parents and relatives among informal sources and university placement cell, agricultural officers and consultants among formal sources were utilized by majority of the students. | J95: C | K95: „UAS“ = University of Agricultural Sciences Bangalore | L95: C | N95: da
A96: 92 | B96: 2012 | C96: Functional Characterization of Drosophila microRNAs by a Novel in Vivo Library | D96: Genetics | E96: MicroRNA in disease regulation | F96: https://openalex.org/W2140100489 | G96: https://doi.org/10.1534/genetics.112.145383 | H96: uas | I96: Animal microRNAs (miRNA) are implicated in the control of nearly all cellular functions. Due to high sequence redundancy within the miRNA gene pool, loss of most of these 21- to 24-bp long RNAs individually does not cause a phenotype. Thus, only very few miRNAs have been associated with clear functional roles. We constructed a transgenic UAS-miRNA library in Drosophila melanogaster that contains 180 fly miRNAs. This library circumvents the redundancy issues by facilitating the controlled misexpression of individual miRNAs and is a useful tool to complement loss-of-function approaches. Demonstrating the effectiveness of our library, 78 miRNAs induced clear phenotypes. Most of these miRNAs wer… | J96: C | K96: „UAS“ = Drosophila | L96: C | N96: ne
A97: 93 | B97: 2021 | C97: Examination of shape memory polymer-auxetic landing gears on landing approach for quadcopter | D97: Materials Today Proceedings | E97: Robotic Locomotion and Control | F97: https://openalex.org/W3170301160 | G97: https://doi.org/10.1016/j.matpr.2021.05.030 | H97: uav, uavs | I97: The current work examines the perching and flight stability studies of the auxetic landing gear based on shape memory polymers. UAVs are capable of perch-and-stare missions. Most UAV perching approachesinvolve complicated maneuvering and depend on particular structures such as rough attachment walls or grasping tree branches. Perching is accomplished by integrating a compliant, underactuated gripping foot and a collapsing mechanism of the leg that converts the weight of the rotorcraft into tendon tension for passive action of the foot. In-plane isotropic in tiny deformations, the hexachiral structure. The aim of the research is, however, to enhance the two shock absorption properties and the… | J97: B | K97: Stajni trap kvadkoptera | L97: B | N97: da
A98: 94 | B98: 2021 | C98: R-LOAM: Improving LiDAR Odometry and Mapping With Point-to-Mesh Features of a Known 3D Reference Object | D98: IEEE Robotics and Automation Letters | E98: Robotics and Sensor-Based Localization | F98: https://openalex.org/W3129693044 | G98: https://doi.org/10.1109/lra.2021.3060413 | H98: uav | I98: LiDAR-based odometry and mapping is used in many robotic applications to retrieve the robot's position in an unknown environment and allows for autonomous operation in GPS-denied (e.g., indoor) environments. With a 3D LiDAR sensor, highly accurate localization becomes possible, which enables high quality 3D reconstruction of the environment. In this letter we extend the well-known LOAM framework by leveraging prior knowledge about a reference object in the environment to further improve the localization accuracy. This requires a known 3D model of the reference object and its known position in a global coordinate frame. Instead of only relying on the point features in the mapping module of LO… | J98: B | K98: LiDAR odometrija UAV | L98: B | N98: da
A99: 95 | B99: 2018 | C99: Medical Applications of Drones for Disaster Relief: A Review of the Literature. | D99: PubMed | E99: Disaster Response and Management | F99: https://openalex.org/W2904168886 | H99: drone, drones, uas, unmanned aerial | I99: INTRODUCTION: Rapid progress has been made with unmanned aerial systems (UAS), which are now used in a wide variety of different fields, including media, agriculture, wildlife, and infrastructure. However, the application of UAS for medical purposes, and in particular disaster relief efforts, has been slower to develop. This paper will review and present pertinent studies in the literature. METHODOLOGY: Studies related to drones and medical applications for disaster relief were identified as part of a larger search regarding the civilian application of drones. A search for civilian drone applications was performed in the EBSCO (Elton B. Stephens Company) database. Non-civilian applications a… | J99: B | K99: Medicinski dronovi | L99: B | N99: da
A100: 96 | B100: 2025 | C100: The role of investment in the development of smart agricultural technologies in megacities | D100: Scientific Horizons | E100: Digitalization and Economic Development in Agriculture | F100: https://openalex.org/W4412922984 | G100: https://doi.org/10.48077/scihor6.2025.150 | H100: drones | I100: The aim of the study was to analyse the role of investments in the development of smart agricultural technologies in the agro-industrial complex of various regions, with a focus on the implementation of these technologies in Azerbaijan. The study analysed current investment trends in smart agricultural technologies in North America, Europe, the Asia-Pacific region, Latin America, the Middle East and Africa for 2023-2024, and assessed their impact on the development of the agro-industrial complex in the period from 2023 to 2034. The investment analysis showed that North America accounted for the largest share of the smart agricultural technology market in 2023-2024 (43%), followed by the Asia… | J100: B | K100: Ulaganja u pametnu poljoprivredu; dronovi spomenuti | L100: B | N100: da
A101: 97 | B101: 2025 | C101: Drones-of-the-Future in Agriculture 5.0 – Automation, integration, and optimisation | D101: Agricultural Systems | E101: UAV Applications and Optimization | F101: https://openalex.org/W4415601036 | G101: https://doi.org/10.1016/j.agsy.2025.104543 | H101: drone, drones | I101: CONTEXT The adoption of drones within Agriculture 5.0 is transforming farming into a service-oriented and data-driven system. This study provides a state-of-art review of Drone-as-a-Service (DaaS), evaluating applications across crop monitoring, soil assessment, livestock surveillance, harvest forecasting, and post-harvest logistics. OBJECTIVE This review propose a systems-level framework to guide future research, regulation, and deployment of drones within Agriculture 5.0. METHODS The study synthesises datasets from published technical standards, communication protocols, interoperability studies, and agricultural service platforms, complemented by tabulated evidence on drone functions, inte… | J101: A | K101: Pregled: dronovi u poljoprivredi 5.0 | L101: A | N101: da
A102: 98 | B102: 2020 | C102: Low-Cost Ka-Band Cloud Radar System for Distributed Measurements within the Atmospheric Boundary Layer | D102: Remote Sensing | E102: Atmospheric aerosols and clouds | F102: https://openalex.org/W3106723231 | G102: https://doi.org/10.3390/rs12233965 | H102: drone | I102: Radars are used to retrieve physical parameters related to clouds and fog. With these measurements, models can be developed for several application fields such as climate, agriculture, aviation, energy, and astronomy. In Chile, coastal fog and low marine stratus intersect the coastal topography, forming a thick fog essential to sustain coastal ecosystems. This phenomenon motivates the development of cloud radars to boost scientific research. In this article, we present the design of a Ka-band cloud radar and the experiments that prove its operation. The radar uses a frequency-modulated continuous-wave with a carrier frequency of 38 GHz. By using a drone and a commercial Lidar, we were able t… | J102: B | K102: Radar oblaka provjeren dronom | L102: B | N102: da
A103: 99 | B103: 2021 | C103: Estimating fractional vegetation cover of maize under water stress from UAV multispectral imagery using machine learning algorithms | D103: Computers and Electronics in Agriculture | E103: Remote Sensing in Agriculture | F103: https://openalex.org/W3198108106 | G103: https://doi.org/10.1016/j.compag.2021.106414 | H103: uav | I103: (sažetak nije dostupan — otvoriti poveznicu) | J103: A | K103: Kukuruz, vodni stres, UAV | L103: A | N103: da
A104: 100 | B104: 2009 | C104: The genetic architecture of reproductive differences in workers of Africanized and European honey bees, Apis mellifera | D104: NC Digital Online Collection of Knowledge and Scholarship (The University of North Carolina at Greensboro) | E104: Insect and Arachnid Ecology and Behavior | F104: https://openalex.org/W1505446208 | H104: drones | I104: The Western Honeybee (Apis mellifera) displays a special form of social behavior called eusociality. The evolution of its reproductively specialized castes and social behavior from a solitary ancestor may be explained by the reproductive ground plan hypothesis. This hypothesis predicts a relationship between the variation of ovary size and -activity and social behavior. At the phenotypic level, ovary size has been associated with a whole set of behavioral phenotypes, known as the pollen hoarding syndrome. While many of these phenotypes are potentially influenced by regulatory pathways, involving juvenile hormone and vitellogenin, the exact genetic links between ovary size determination and s… | J104: C | K104: „drones“ = trutovi (pčele) | L104: C | N104: ne

Sheet Uzorak_50_rano
A1: Uzorak B: 50 slučajnih zapisa sirovog upita, 2005.–2015. (seed 20260829)
A2: Žuti stupac = KONAČNA OCJENA (A/B/C), popunite ili potvrdite; prijedlog (AI) je samo pomoć.
A4: # | B4: Godina | C4: Naslov | D4: Časopis / izvor | E4: OpenAlex tema | F4: OpenAlex ID (poveznica) | G4: DOI | H4: UAV pojam | I4: Sažetak (skraćen) | J4: Prijedlog (AI) | K4: Obrazloženje prijedloga | L4: KONAČNA OCJENA | M4: Napomena ocjenjivača | N4: U čistom upitu (da/ne)
A5: 1 | B5: 2011 | C5: Section News | D5: Anthropology News | E5: Historical and Cultural Archaeology Studies | F5: https://openalex.org/W4233763440 | G5: https://doi.org/10.1111/j.1556-3502.2011.52925.x | H5: (nije u naslovu/sažetku) | I5: Abstract: For your convenience, this month's Section News PDF includes bookmarks for each section. After opening the PDF, select the “Bookmark” tab on the left side of your screen, and click on the name of the section you are interested in reading. AMERICAN ETHNOLOGICAL SOCIETY (AES): Caitrin Lynch, ed. “Occupy Wall Street” by M Elle Saine ANTHROPOLOGY AND ENVIRONMENT SECTION (A&E): Amelia Moore, ed. “Understanding Interdisciplinarity in the Long Term Ecological Research Network” by Rebecca Garvoille ARCHEOLOGY DIVISION (AD): E Christian Wells, ed. “Continuing Professional Education in Archaeology: A New Program from RPA” by Ian Burrow ASSOCIATION OF BLACK ANTHROPOLOGISTS (ABA): Bianca C Wil… | J5: C | K5: Nema UAV pojma (Section News) | L5: C | N5: da
A6: 2 | B6: 2013 | C6: Different Fish-Eating Habits and Cytokine Production in Chronic Urticaria with and without Sensitization against the Fish-Parasite Anisakis simplex | D6: Allergology International | E6: Urticaria and Related Conditions | F6: https://openalex.org/W1986281840 | G6: https://doi.org/10.2332/allergolint.12-oa-0504 | H6: uas | I6: BACKGROUND: Anisakis simplex sensitization has been associated with acute, but also with chronic urticaria. The objective of this study is to characterize chronic urticaria with (CU+) and without sensitization (CU-) against the ubiquitous fish parasite A. simplex in a transversal and longitudinal evaluation. METHODS: 16 CU+ and 22 CU- patients were included and assessed for Urticaria activity score (UAS), fish-eating habits by standardized questionnaire and cytokine production (assessed by flow cytometric bead-based array) of peripheral blood mononuclear cells after stimulation with A. simplex extract or Concanavalin A (Con A). Patients were randomly put on a fish-free diet for three months … | J6: C | K6: „UAS“ = urticaria activity score | L6: C | N6: ne
A7: 3 | B7: 2014 | C7: Synthesis, helical conformation, and infrared emissivity property study of optically active substituted polyacetylenes derived from serine | D7: Journal of Applied Polymer Science | E7: Synthesis and Properties of Aromatic Compounds | F7: https://openalex.org/W2060213987 | G7: https://doi.org/10.1002/app.41210 | H7: (nije u naslovu/sažetku) | I7: ABSTRACT Serine‐based monosubstituted acetylene monomers were synthesized and polymerized with rhodium zwitterion catalyst in THF to afford optically active polyacetylene derivatives (LPA and DPA) and corresponding racemic polyacetylenes (RPA) with moderate molecular weights in good yields. All of the substituted polyacetylenes (SPA) were characterized by FT‐IR, NMR, GPC, UV‐Vis spectroscopy, circular dichroism (CD) spectroscopy, and TGA. LPA and DPA were soluble in common organic solvents and possessed single‐handed helical conformation according to their intense Cotton effect and large specific rotations, while RPA presented random coiled polymer chain. The characterization results showed … | J7: C | K7: Nema UAV pojma (kemija) | L7: C | N7: da
A8: 4 | B8: 2015 | C8: Potential of aerial robotics in crop production: high resolution NIR/VIS imagery obtained by automated unmanned aerial vehicle (UAV) in estimation of botanical composition of alfalfa-grass mixture | E8: Remote Sensing in Agriculture | F8: https://openalex.org/W2564183401 | H8: uav, unmanned aerial | I8: (sažetak nije dostupan — otvoriti poveznicu) | J8: A | K8: Lucerna-trava, UAV NIR/VIS | L8: A | N8: da
A9: 5 | B9: 2007 | C9: Real-Time Optimal Mission Scheduling and Flight Path Selection | D9: IEEE Transactions on Automatic Control | E9: Vehicle Routing Optimization Methods | F9: https://openalex.org/W2110698131 | G9: https://doi.org/10.1109/tac.2007.899048 | H9: uavs | I9: We consider a mission in which m UAVs with a capacity limit q each visit n(les mq) targets in a hostile environment in a cooperative manner (and return to where they departed from) such that the cost reflecting operating time and risk exposed is minimized. We first propose a mixed-integer linear programming (MILP) formulation which exactly solves the problem and then propose four alternative MILP formulations which are computationally less intensive and, therefore, suited for real-time purposes, but yield a theoretically guaranteed suboptimal solution. The main contributions of this note are an exact but compact MILP formulation, using a room concept, and four nonexact formulations, each one… | J9: B | K9: Vojno planiranje misija UAV-a | L9: B | N9: da
A10: 6 | B10: 2011 | C10: UAV operated Hyperspectral Imager for forest and agriculture applications | E10: Infrared Target Detection Methodologies | F10: https://openalex.org/W2970191788 | H10: uav | I10: (sažetak nije dostupan — otvoriti poveznicu) | J10: A | K10: Hiperspektralni senzor za šume i poljoprivredu | L10: A | N10: da
A11: 7 | B11: 2005 | C11: The HhH(2)/NDD Domain of the Drosophila Nod Chromokinesin-like Protein Is Required for Binding to Chromosomes in the Oocyte Nucleus | D11: Genetics | E11: Chromosomal and Genetic Variations | F11: https://openalex.org/W2147646531 | G11: https://doi.org/10.1534/genetics.105.047464 | H11: uas | I11: Nod is a chromokinesin-like protein that plays a critical role in segregating achiasmate chromosomes during female meiosis. The C-terminal half of the Nod protein contains two putative DNA-binding domains. The first of these domains, known as the HMGN domain, consists of three tandemly repeated high-mobility group N motifs. This domain was previously shown to be both necessary and sufficient for binding of the C-terminal half of Nod to mitotic chromosomes in embryos. The second putative DNA-binding domain, denoted HhH(2)/NDD, is a helix-hairpin-helix(2)/Nod-like DNA-binding domain. Although the HhH(2)/NDD domain is not required or sufficient for chromosome binding in embryos, several well-ch… | J11: C | K11: „UAS“ = Drosophila | L11: C | N11: ne
A12: 8 | B12: 2007 | C12: New Honeybee Toxicity Studies in RCC | D12: 한국농약과학회 학술발표대회 논문집 | E12: Insect and Pesticide Research | F12: https://openalex.org/W2270439011 | H12: drones | I12: Honeybees (Apis mellifera L.) are important pollinators of agricultural crops and orchards, found in both urban and natural landscapes. Honey-bees are social insects living in hives controlled by a queen and supported by worker bees (females) and drones (males). During the summer months, a colony presided over by a queen consists of approximately 10,000 to 30,000 worker bees and 100 to 1,000 drones. Colonies can be wild, but often are domesticated, specifically established by beekeepers for pollination and honey production. Worker bees forage several miles from the hive to gather pollen and nectar from many flower species. They are also known to collect honeydew produced by aphids. Honeybees… | J12: C | K12: „drones“ = trutovi | L12: C | N12: ne
A13: 9 | B13: 2015 | C13: NIMG-60TREATMENT RESPONSE KINETICS AND EXCEPTIONAL SURVIVAL IN GLIOBLASTOMA | D13: Neuro-Oncology | E13: Glioma Diagnosis and Treatment | F13: https://openalex.org/W2554945760 | G13: https://doi.org/10.1093/neuonc/nov225.60 | H13: (nije u naslovu/sažetku) | I13: Although glioblastoma (GBM) is considered a uniformly fatal disease, roughly 2-5% of GBM patients survive longer than 5 years. In this study, we sought to elucidate how response to treatment may be similar or different in long-term survivors (LTS) defined as living longer than 3 years (n = 12) versus patients with typical overall survival (<3 years) (n = 36). Pre-treatment, response to radiation, time to minimum volume, and post-treatment tumor growth kinetics were compared. Newly diagnosed GBM patients with 2 pre-treatment MRIs and 1 post-treatment MRI treated with adjuvant chemoradiation were included. Patients were classified by overall survival: LTS >3 years and the typical cohort as <3 … | J13: C | K13: Nema UAV pojma (glioblastom) | L13: C | N13: ne
A14: 10 | B14: 2007 | C14: Not So Good Old Summertime | D14: Canadian Journal of Infectious Diseases and Medical Microbiology | E14: Viral Infections and Vectors | F14: https://openalex.org/W1950343464 | G14: https://doi.org/10.1155/2007/710513 | H14: drone | I14: Visions of another glorious Canadian summer shimmer before us – a world of light and warmth after a cold, dark season. Cottages, lakes, barbecues and long, warm evenings beckon. There will be hikes through the bush, socializing over hamburgers, drinks on the deck at sunset, and sand and swimming at the beach. What is wrong with this picture? It's the persistent drone of messages alerting us to an ever-increasing danger with summertime and summer pursuits. There is no need to consider noninfectious problems such as skin cancer or off-road vehicle accidents; there is sufficient alarm considering only the infectious diseases. Bird watchers now wonder if the glory of the spring migration hera… | J14: C | K14: „drone“ = zujanje poruka | L14: C | N14: ne
A15: 11 | B15: 2014 | C15: Synthetic Lethality Induced by a Strong Drosophila Enhancer of Expanded Polyglutamine Tract | D15: Open Journal of Genetics | E15: Genetic Neurodegenerative Diseases | F15: https://openalex.org/W2014279843 | G15: https://doi.org/10.4236/ojgen.2014.44028 | H15: uas | I15: Proteins containing an expanded polyglutamine tract are neurotoxins. The expanded polyglutamine proteins influence a variety of cellular functions. In Drosophila the GMR-Gal4/UAS expression system has been widely used in an eye-based model to study human neurodegenerative diseases. This system has facilitated the isolation and characterization of abundant Drosophilagenes that interact with the expanded polyglutamine proteins. We used the GMR-Gal4/UAS system to express three proteins containing an expanded polyglutamine tract, or an expanded polyglutamine tract alone. Doubling the dose of these proteins resulted in pupal lethality, indicating that these toxic proteins induced a sensitized con… | J15: C | K15: „UAS“ = Drosophila | L15: C | N15: ne
A16: 12 | B16: 2010 | C16: A MAG for the Twenty First Century: Lethal, Lighter, Energy Efficient, and Cheaper | E16: Rocket and propulsion systems research | F16: https://openalex.org/W329917040 | H16: uas, unmanned aircraft | I16: Abstract : The Marine Corps should acquire the OV-10X, a fixed wing light attack aircraft, and group that newly formed squadron with future Unmanned Aircraft System (UAS) squadrons and the newly armed KC-130 squadrons into a common Marine Aircraft Group (MAG) in order to achieve several significant goals. First, this proposal addresses the MV-22 Osprey escort gap and the training and personnel limitations of the UAS and KC-130 communities by establishing a primary career path for UAS officer aircrew and integrated aircrew training across all three squadrons. Second, it provides a model to supply additional U.S. Marine Corps airframes, in support of an identified U.S. Air Force and U.S. Navy … | J16: B | K16: Vojni UAS eskadroni | L16: B | N16: da
A17: 13 | B17: 2013 | C17: EXTENDED KALMAN FILTER BASED AIRBORNE SIMULTANEOUS LOCALIZATION AND MAPPING | D17: DOAJ (DOAJ: Directory of Open Access Journals) | E17: Robotics and Sensor-Based Localization | F17: https://openalex.org/W2970423453 | H17: uav, uavs | I17: UAVs are expected to perform all or part of its mission as autonomous in accordance with predefined at the manufacture objectives and prerequest of safe autonomous navigation is to detect the UAV location precisely. Nowadays the most common method for location detection is the use of Global Navigation Satellite Systems (GNSS). Howewer but it is a challenge for researchers to determine location in GNSS denied enviroments. Although new methods are emerging continuously, the most notably one is Simultaneous Localization and Mapping (SLAM), which is a good solution when both UAVs position and region map are not known. In this research, formulas of Extended Kalman Filter (EKF) based (A-SLAM) Airb… | J17: B | K17: SLAM za UAV | L17: B | N17: da
A18: 14 | B18: 2015 | C18: Diagnostics-in-a-Suitcase: Development of a portable and rapid assay for the detection of the emerging avian influenza A (H7N9) virus | D18: Journal of Clinical Virology | E18: Influenza Virus Research Studies | F18: https://openalex.org/W1949466286 | G18: https://doi.org/10.1016/j.jcv.2015.05.004 | H18: (nije u naslovu/sažetku) | I18: BACKGROUND: In developing countries, equipment necessary for diagnosis is only available in few central laboratories, which are less accessible and of limited capacity to test large numbers of incoming samples. Moreover, the transport conditions of samples are inadequate, therefore leading to unreliable results. OBJECTIVES: The development of a rapid, inexpensive, and simple test would allow mobile detection of viruses. STUDY DESIGN: A suitcase laboratory "Diagnostics-in-a-Suitcase" (56cm×45.5cm×26.5cm) containing all reagents and devices necessary for performing a reverse transcription recombinase polymerase amplification (RT-RPA) assay was developed. As an example, two RT-RPA assays were e… | J18: C | K18: Nema UAV pojma (dijagnostika) | L18: C | N18: da
A19: 15 | B19: 2007 | C19: RNAi Knockdown of Nopp140 InducesMinute-like Phenotypes inDrosophila | D19: Molecular Biology of the Cell | E19: RNA modifications and cancer | F19: https://openalex.org/W2144049291 | G19: https://doi.org/10.1091/mbc.e07-01-0074 | H19: uas | I19: Nopp140 associates with small nucleolar RNPs to chaperone pre-rRNA processing and ribosome assembly. Alternative splicing yields two isoforms in Drosophila: Nopp140-True is homologous to vertebrate Nopp140 particularly in its carboxy terminus, whereas Nopp140-RGG contains a glycine and arginine-rich (RGG) carboxy terminus typically found in vertebrate nucleolin. Loss of ribosome function or production at critical points in development leads to Minute phenotypes in Drosophila or the Treacher Collins syndrome (TCS) in humans. To ascertain the functional significance of Nopp140 in Drosophila development, we expressed interfering RNA using the GAL4/UAS system. Reverse transcription-PCR showed va… | J19: C | K19: „UAS“ = Drosophila | L19: C | N19: ne
A20: 16 | B20: 2014 | C20: Pros of unmanned aerial site viewing | D20: Renewable energy focus | E20: Hungarian Social, Economic and Educational Studies | F20: https://openalex.org/W1996228435 | G20: https://doi.org/10.1016/s1755-0084(14)70100-0 | H20: unmanned aerial | I20: (sažetak nije dostupan — otvoriti poveznicu) | J20: B | K20: Pregled gradilišta UAV-om | L20: B | N20: da
A21: 17 | B21: 2013 | C21: Robust Optimal Control of Quadrotor UAVs | D21: IEEE Access | E21: Adaptive Control of Nonlinear Systems | F21: https://openalex.org/W2094917509 | G21: https://doi.org/10.1109/access.2013.2260794 | H21: uav, uavs, unmanned aerial | I21: This paper provides the design and implementation of an L1-optimal control of a quadrotor unmanned aerial vehicle (UAV). The quadrotor UAV is an underactuated rigid body with four propellers that generate forces along the rotor axes. These four forces are used to achieve asymptotic tracking of four outputs, namely the position of the center of mass of the UAV and the heading. With perfect knowledge of plant parameters and no measurement noise, the magnitudes of the errors are shown to exponentially converge to zero. In the case of parametric uncertainty and measurement noise, the controller yields an exponential decrease of the magnitude of the errors in an L1-optimal sense. In other words, … | J21: B | K21: Upravljanje kvadrotorom | L21: B | N21: da
A22: 18 | B22: 2008 | C22: Effect of ferromagnetic spin fluctuations on the electronic states in NaxCoO2 based on two-dimensional triangular lattice 11-band d–p model | D22: Journal of Physics and Chemistry of Solids | E22: Physics of Superconductivity and Magnetism | F22: https://openalex.org/W1983903878 | G22: https://doi.org/10.1016/j.jpcs.2008.06.078 | H22: (nije u naslovu/sažetku) | I22: (sažetak nije dostupan — otvoriti poveznicu) | J22: C | K22: Nema UAV pojma (fizika) | L22: C | N22: da
A23: 19 | B23: 2013 | C23: The Rise of Small UAVs in Precision Agriculture | E23: Crop Yield and Soil Fertility | F23: https://openalex.org/W2526391094 | H23: uavs, unmanned aerial | I23: Abstract. Unmanned aerial vehicles (UAVs) were originally designed for dull, dirty, and often dangerous work in military operations. However, like other military technologies, such as GPS, UAVs will soon find more use in civilian applications. In fact, the Federal Aviation Administration (FAA) is congressionally mandated to open U.S. air space for the commercial use of UAVs by 2015. A conservative estimate by an aviation economist projected a $13.6 billion impact of this technology in the first three years of approved commercial use (2015-2018), and among all potential markets for UAVs, precision agriculture is considered to be the largest. This will have significant implications for precisi… | J23: A | K23: Pregled: mali UAV-i u preciznoj poljoprivredi | L23: A | N23: da
A24: 20 | B24: 2014 | C24: Detecting Cars in UAV Images With a Catalog-Based Approach | D24: IEEE Transactions on Geoscience and Remote Sensing | E24: Advanced Image and Video Retrieval Techniques | F24: https://openalex.org/W2043552486 | G24: https://doi.org/10.1109/tgrs.2013.2296351 | H24: uav, unmanned aerial | I24: This paper presents a new method for the automatic detection of cars in unmanned aerial vehicle (UAV) images acquired over urban contexts. UAV images are characterized by an extremely high spatial resolution, which makes the detection of cars particularly challenging. The proposed method starts with a screening operation in which the asphalted areas are identified in order to make the car detection process faster and more robust. Subsequently, filtering operations in the horizontal and vertical directions are performed to extract histogram-of-gradient features and to yield a preliminary detection of cars after the computation of a similarity measure with a catalog of cars used as reference. … | J24: B | K24: Detekcija automobila u UAV snimkama | L24: B | N24: da
A25: 21 | B25: 2015 | C25: Using robotic aircraft and intelligent surveillance systems for orange hawkweed detection | D25: Plant protection quarterly | E25: Biological Control of Invasive Species | F25: https://openalex.org/W2410638667 | H25: uavs, unmanned aerial | I25: Remote sensing using robotic aircraft (either Unmanned Aerial Vehicles (UAVs) or remotely piloted) can be an efficient and cost-effective way of collecting geo-spatial information over large areas. Furthermore, the large amounts of data collected by these systems can be handled by intelligent software systems that are able to autonomously classify the data. The Australian Centre for Field Robotics (ACFR) has been using aerial robots for environmental monitoring and has developed algorithms to support weed detection and mapping projects. The algorithm research at the ACFR has led to various intelligent detection and mapping software systems for accurate terrain mapping, vegetation segmentatio… | J25: A | K25: Detekcija korova (hawkweed) UAV-om | L25: A | N25: da
A26: 22 | B26: 2013 | C26: An Improved Marriage in Honey Bees Optimization Algorithm for Single Objective Unconstrained Optimization | D26: The Scientific World JOURNAL | E26: Metaheuristic Optimization Algorithms Research | F26: https://openalex.org/W1987545539 | G26: https://doi.org/10.1155/2013/370172 | H26: drone | I26: Marriage in honey bees optimization (MBO) is a metaheuristic optimization algorithm developed by inspiration of the mating and fertilization process of honey bees and is a kind of swarm intelligence optimizations. In this study we propose improved marriage in honey bees optimization (IMBO) by adding Levy flight algorithm for queen mating flight and neighboring for worker drone improving. The IMBO algorithm's performance and its success are tested on the well-known six unconstrained test functions and compared with other metaheuristic optimization algorithms. | J26: C | K26: Algoritam „ženidbe pčela“ | L26: C | N26: ne
A27: 23 | B27: 2015 | C27: DETERMINATION OF THE AERODYNAMIC CHARACTERISTICS FOR AGRICULTURAL UAVS IN UNSTEADY FLOW | D27: Information systems mechanics and control | E27: Aerospace Engineering and Control Systems | F27: https://openalex.org/W2563637060 | G27: https://doi.org/10.20535/2219-380411201450598 | H27: uav, uavs | I27: The purpose of work is estimation of unsteady flow influence on the aerodynamic characteristics of the aircraft with several lifting surfaces. The work presents characteristic features of specialized agricultural aircraft operation based on the specifics of modern agriculture.The most significant factors affecting the efficiency agricultural aircraft were identified.The features of a non-stationary aerodynamics for agricultural aircraft with several supporting surfaces were viewed and the calculation results of aerodynamic characteristics, which depend on the basic parameters of the lifting surfaces, were shown. The mutual influence of lifting surfaces on the aerodynamic characteristics of t… | J27: A | K27: Aerodinamika poljoprivrednih UAV-a | L27: A | N27: da
A28: 24 | B28: 2009 | C28: Modeling Glioma Growth and Invasion in Drosophila melanogaster | D28: Neoplasia | E28: Hippo pathway signaling and YAP/TAZ | F28: https://openalex.org/W1533413123 | G28: https://doi.org/10.1593/neo.09576 | H28: uas | I28: Glioblastoma is the most common and most malignant intrinsic human brain tumor, characterized by extensive invasion and proliferation of glial (astrocytic) tumor cells, frequent activation of tyrosine kinase receptor signaling pathways, relative resistance to chemotherapy and radiotherapy, and poor prognosis. Using the Gal4-UAS system, we have produced glioma models in Drosophila by overexpressing homologs of human tyrosine kinase receptors under control of the glia-specific promoter reversed polarity (repo). Glial overexpression of activated epidermal growth factor receptor (EGFR) resulted in enhanced proliferation and migration of larval glial cells with increased numbers in the eye imagin… | J28: C | K28: „UAS“ = Drosophila | L28: C | N28: ne
A29: 25 | B29: 2013 | C29: Potential uses of small unmanned aircraft systems ( UAS ) in weed research | D29: Weed Research | E29: Biological Control of Invasive Species | F29: https://openalex.org/W2016718980 | G29: https://doi.org/10.1111/wre.12026 | H29: uas, unmanned aerial, unmanned aircraft | I29: Summary Small unmanned aerial systems (UAS) with cameras have not been adopted in weed research, but offer low‐cost sensing with high flexibility in terms of spatial resolution. A small rotary‐wing UAS was tested as part of a search for an inexpensive, user‐friendly and reliable aircraft for practical applications in UAS imagery weed research. In two experiments with post‐emergence weed harrowing in barley, the crop resistance parameter, which reflects the crop response to harrowing, was unaffected by image capture altitude in the range from 1 to 50 m. This corresponded to image spatial resolution in the range from 0.3 to 17.1 mm per pixel. This finding is important because spatial resolutio… | J29: A | K29: UAS u istraživanju korova | L29: A | N29: da
A30: 26 | B30: 2012 | C30: Complex pleiotropy characterizes the pollen hoarding syndrome in honey bees (Apis mellifera L.) | D30: Behavioral Ecology and Sociobiology | E30: Plant and animal studies | F30: https://openalex.org/W2073174331 | G30: https://doi.org/10.1007/s00265-012-1400-x | H30: (nije u naslovu/sažetku) | I30: (sažetak nije dostupan — otvoriti poveznicu) | J30: C | K30: Nema UAV pojma (pčele) | L30: C | N30: ne
A31: 27 | B31: 2014 | C31: Drones and the Question of “The Human” | D31: Ethics & International Affairs | E31: Middle East and Rwanda Conflicts | F31: https://openalex.org/W2103727054 | G31: https://doi.org/10.1017/s0892679414000185 | H31: drone, drones | I31: Domino's Pizza is testing “Domicopter” drones to deliver pizzas, which will compete with Taco Bell's “Tacocopter” drones. Not to be outdone, Amazon is working on an army of delivery drones that will cut out the postal service. In Denmark, farmers use drones to inspect fields for the appearance of harmful weeds, which reduces herbicide use as the drones directly apply pesticides only where it is needed. Environmentalists send drones into glacial caves or into deep waters, gathering data that would be too dangerous or expensive for human scientists to procure. Federal Express dreams of pilotless aerial and terrestrial drones that will transport goods more cheaply, reliably, and safely than veh… | J31: B | K31: Dronovi i „ljudsko“ (dostava) | L31: B | N31: da
A32: 28 | B32: 2013 | C32: Dietary chlorantraniliprole suppresses reproduction in worker bumblebees | D32: Pest Management Science | E32: Insect and Pesticide Research | F32: https://openalex.org/W1930770503 | G32: https://doi.org/10.1002/ps.3504 | H32: drones | I32: BACKGROUND: Pollinators such as the bumblebee, Bombus terrestris, fulfil a crucial role in agriculture. In this context, tests were conducted with the insecticide chlorantraniliprole (Coragen®) as a model compound active on the ryanodine receptor of insects. RESULTS: Chronic oral exposure via pollen induced lethargic behaviour in B. terrestris workers and their offspring (drones). Indeed, in nests exposed to 0.4 mg L(-1) , representing 1/100 of the concentration recommended for use in the field, workers and drones did not take their defensive position upon stimulation and they were less active than non-exposed insects. The different risk assessment tests used here demonstrated that contact a… | J32: C | K32: „drones“ = trutovi bumbara | L32: C | N32: ne
A33: 29 | B33: 2015 | C33: IL-10–producing forkhead box protein 3–negative regulatory T cells inhibit B-cell responses and are involved in systemic lupus erythematosus | D33: Journal of Allergy and Clinical Immunology | E33: T-cell and B-cell Immunology | F33: https://openalex.org/W2201837705 | G33: https://doi.org/10.1016/j.jaci.2015.06.044 | H33: (nije u naslovu/sažetku) | I33: (sažetak nije dostupan — otvoriti poveznicu) | J33: C | K33: Nema UAV pojma (imunologija) | L33: C | N33: da
A34: 30 | B34: 2014 | C34: The evaluation of unmanned aerial system-based photogrammetry and terrestrial laser scanning to generate DEMs of agricultural watersheds | D34: Geomorphology | E34: Remote Sensing and LiDAR Applications | F34: https://openalex.org/W1971575659 | G34: https://doi.org/10.1016/j.geomorph.2014.02.016 | H34: unmanned aerial | I34: (sažetak nije dostupan — otvoriti poveznicu) | J34: A | K34: UAS fotogrametrija DEM poljoprivrednih slivova | L34: A | N34: da
A35: 31 | B35: 2012 | C35: That Other Story | D35: The Thomas Wolfe review | E35: Cuban History and Society | F35: https://openalex.org/W329866896 | H35: drone | I35: A too-dark rope of oil drained down a few inches to the right of Tomby's face where he lay under Baby Blue, his hissed profanity muffled against the undercarriage. Car was his only hope of not getting trapped on base. He held his breath at a sound that might have been the crunch of safety boots, but the ground was quiet. The guy who sold him the car a couple hundred miles ago had clearly just added a pint to compensate for the slow leak he forgot to mention. Probably because he had orders for Vietnam. Selling it cheap. Thing about that guy was he lacked the boring gung-ho swagger. The gray eyes also didn't hurt. Tomby wiped and replaced the cap and tightened it down with his wrench and pushe… | J35: C | K35: Književni tekst | L35: C | N35: da
A36: 32 | B36: 2008 | C36: Concentration-Coverage Curve: A Tool for Ecological Studies. Copyright: Statistics Canada. | D36: Open Scholarship Institutional Repository (Washington University in St. Louis) | E36: Soil and Water Nutrient Dynamics | F36: https://openalex.org/W2952638625 | H36: uas | I36: BACKGROUND: A selective approach may be used in an ecological study where the aim is to choose a subset of units of analysis (UAs) and produce interpretations about a population of interest (PI) based solely on those UAs. The results for the PI will be reliable if that population is concentrated in the selected UAs and rare in other UAs. This article presents a graphical tool that helps determine whether these conditions are satisfied. DATA AND METHODS: Data on the Inuit and Métis ancestry populations from the 1996 Census of Canada are used for illustrative purposes. Based on a classification statistics table, a concentration-coverage curve can be created for a given PI. The shape of the cur… | J36: C | K36: „UAs“ = units of analysis | L36: C | N36: da
A37: 33 | B37: 2011 | C37: Agronegócio e novas regionalizações no Brasil | D37: Revista Brasileira de Estudos Urbanos e Regionais | E37: Rural Development and Agriculture | F37: https://openalex.org/W1562086546 | G37: https://doi.org/10.22296/2317-1529.2011v13n2p153 | H37: rpas | I37: As transformações ocorridas na atividade agropecuária brasileira nas últimas cinco décadas têm profundos impactos sobre a (re)organização do território brasileiro, resultando em novos arranjos territoriais. Entre esses, destacam-se os inerentes ao agronegócio globalizado, áreas escolhidas para receber os mais expressivos investimentos produtivos do setor, representando suas áreas mais competitivas, as quais denominamos Regiões Produtivas Agrícolas (RPAs). Os principais objetivos desse texto são: debater a noção de RPA; apresentar os elementos de identificação e caracterização da mencionada região; aperfeiçoar o caminho analítico que vem sendo trilhado e incrementar a noção no contexto dos es… | J37: C | K37: „RPAs“ = portugalski akronim | L37: C | N37: da
A38: 34 | B38: 2015 | C38: Fontan Circulatory Assist Device1 | D38: Journal of Medical Devices | E38: Mechanical Circulatory Support Devices | F38: https://openalex.org/W1534497196 | G38: https://doi.org/10.1115/1.4030136 | H38: (nije u naslovu/sažetku) | I38: The Fontan physiology is essentially a form of chronic right heart failure associated with elevated central venous pressures (CVP). Due to improvements in operative procedures, timing, staging, and management, operative mortality is now less than 5% and survival at 20 yr is 84% [1]. However, morbidity is significant due to venous congestion and elevated pulmonary vascular resistance (PVR), progressive ventricular dysfunction, dysrhythmias, hypoxemia, and protein-losing enteropathy. Heart transplantation in failed Fontan patients yields survival similar to non-Fontan patients. However, many Fontan patients are not considered for transplantation due to multi-organ failure, high PVR, prior surg… | J38: C | K38: Nema UAV pojma (medicina) | L38: C | N38: ne
A39: 35 | B39: 2010 | C39: Tracking the potato late blight pathogen in the atmosphere using unmanned aerial vehicles and Lagrangian modeling | D39: Agricultural and Forest Meteorology | E39: Plant Pathogens and Resistance | F39: https://openalex.org/W2094160436 | G39: https://doi.org/10.1016/j.agrformet.2010.10.013 | H39: unmanned aerial | I39: (sažetak nije dostupan — otvoriti poveznicu) | J39: A | K39: Patogen krumpira praćen UAV-om | L39: A | N39: da
A40: 36 | B40: 2013 | C40: A Survey and Categorization of Small Low-Cost Unmanned Aerial Vehicle System Identification | D40: Journal of Intelligent & Robotic Systems | E40: Aerospace and Aviation Technology | F40: https://openalex.org/W1993861190 | G40: https://doi.org/10.1007/s10846-013-9931-6 | H40: unmanned aerial | I40: (sažetak nije dostupan — otvoriti poveznicu) | J40: B | K40: Identifikacija sustava malih UAV-a | L40: B | N40: da
A41: 37 | B41: 2012 | C41: Premature birth is associated with not fully differentiated contractile smooth muscle cells in human umbilical artery | D41: Placenta | E41: Congenital heart defects research | F41: https://openalex.org/W2026767284 | G41: https://doi.org/10.1016/j.placenta.2012.03.005 | H41: (nije u naslovu/sažetku) | I41: (sažetak nije dostupan — otvoriti poveznicu) | J41: C | K41: Nema UAV pojma (medicina) | L41: C | N41: da
A42: 38 | B42: 2015 | C42: UAS imaging-based decision tools for arid winter wheat and irrigated potato production management | D42: International Journal of Remote Sensing | E42: Remote Sensing in Agriculture | F42: https://openalex.org/W2221198076 | G42: https://doi.org/10.1080/01431161.2015.1117685 | H42: uas, unmanned aerial | I42: Small unmanned aerial systems (UAS) are gaining global attention for rapid image-based decision making in agricultural production. In this study, the aim was to evaluate UAS-based imagery for rapid assessment of wheat winter survival and spring stand in winter wheat production and crop necrosis in potato production. Both are critical aspects of field (arid) and row (irrigated) crop farming practices. Aerial images from 97 hard and 352 soft single nucleotide polymorphism winter wheat plots, and 32 potato field plots (with 1 and 2 years of green manure applications) were acquired using a multi-band imaging sensor integrated with UAS. The UAS-based imagery was useful in evaluating winter wheat … | J42: A | K42: UAS alati za pšenicu i krumpir | L42: A | N42: da
A43: 39 | B43: 2014 | C43: Experiment of straight and airline flight operation for farmland based on UAV in visual remote mode. | D43: Transactions of the Chinese Society of Agricultural Machinery | E43: Advanced Algorithms and Applications | F43: https://openalex.org/W3159473322 | H43: uav | I43: (sažetak nije dostupan — otvoriti poveznicu) | J43: A | K43: Letovi UAV-a nad oranicama | L43: A | N43: da
A44: 40 | B44: 2009 | C44: A Gain-of-Function Screen Identifying Genes Required for Growth and Pattern Formation of the Drosophila melanogaster Wing | D44: Genetics | E44: Developmental Biology and Gene Regulation | F44: https://openalex.org/W2156710834 | G44: https://doi.org/10.1534/genetics.109.107748 | H44: uas | I44: The Drosophila melanogaster wing is a model system for analyzing the genetic control of organ size, shape, and pattern formation. The formation of the wing involves a variety of processes, such as cell growth, proliferation, pattern formation, and differentiation. These developmental processes are under genetic control, and many genes participating in specific aspects of wing development have already being characterized. In this work, we aim to identify novel genes regulating wing growth and patterning. To this end, we have carried out a gain-of-function screen generating novel P-UAS (upstream activating sequences) insertions allowing forced gene expression. We produced 3,340 novel P-UAS ins… | J44: C | K44: „UAS“ = Drosophila | L44: C | N44: ne
A45: 41 | B45: 2005 | C45: The Purine Synthesis Gene Prat2 Is Required for Drosophila Metamorphosis, as Revealed by Inverted-Repeat-Mediated RNA Interference | D45: Genetics | E45: CRISPR and Genetic Engineering | F45: https://openalex.org/W2157028755 | G45: https://doi.org/10.1534/genetics.105.045641 | H45: uas | I45: PRAT (phosphoribosylamidotransferase; E.C. 2.4.2.14) catalyzes the first reaction in de novo purine nucleotide biosynthesis. In Drosophila melanogaster, the Prat and Prat2 genes are both highly conserved with PRAT sequences from prokaryotes and eukaryotes. However, Prat2 organization and expression during development is different from Prat. We used RNA interference (RNAi) to knock down expression of both Prat and Prat2 to investigate their functions. Using the GAL4-UAS system, Prat RNAi driven by Act5c-GAL4 or tubP-GAL4 causes variable pupal lethality (48-100%) and approximately 50% female sterility, depending on the transgenic strains and drivers used. This observation agrees with the pheno… | J45: C | K45: „UAS“ = Drosophila | L45: C | N45: ne
A46: 42 | B46: 2015 | C46: Ecological Benefits Evaluation in Ecological Migration Zone Based on Ecological Green Equivalent: A Case Study of Migration Zone in Yanchi County | D46: 亚洲农业研究：英文版 | E46: Land Use and Ecosystem Services | F46: https://openalex.org/W3142025330 | H46: uav | I46: With four ecological migration zones in Huamachi Town of Yanchi County in Ningxia Autonomous Region as the object of study,we carry out the evaluation of ecological benefits in ecological migration zone. Using the SPOT satellite remote sensing image in 2008 and UAV aerophotographic image in 2013,we first monitor and analyze the land use change over five years in the study area,and then adopt ecological green equivalent evaluation model for the evaluation of ecological benefits in the ecological migration zone. Studies have shown that:( i) from 2008 to 2013,the ecological green equivalent in the study area was increased and the ecological environment was improved;( ii) the ecological green eq… | J46: B | K46: Ekološka migracijska zona, UAV | L46: B | N46: da
A47: 43 | B47: 2006 | C47: The cacophony Gene and Repetitive-pattern Phenotypes in Drosophila melanogaster | D47: DigitalCommons (California Polytechnic State University) | E47: Plant Molecular Biology Research | F47: https://openalex.org/W107716246 | H47: uas | I47: The cacophony (cac) gene is located on the X-chromosome of Drosophila and codes for the a-1(pore-forming) subunit of a voltage-gated calcium channel. Certain mutations in this gene result in both an aberrant courtship song and a heartbeat with rate and rhythmicity significantly different from wild-type. The cacS mutants produce songs with polycyclic pulses, increased inter-pulse intervals and enhance pulse amplitudes compared with the songs of wild-type males. Given the repetitive patterns of output that define both courtship song and heartbeat in the cac mutant, the cac gene is a likely candidate for regulating or forming core oscillator components of such behaviors. To establish definitive… | J47: C | K47: „UAS“ = Drosophila | L47: C | N47: ne
A48: 44 | B48: 2015 | C48: Effect of different ratios and levels of nitrogen and phosphorus fertilizers, and top dressing of nitrogen fertilizers on growth and yield of groundnut | E48: Peanut Plant Research Studies | F48: https://openalex.org/W2531922452 | H48: uas | I48: A field experiment was carried out during 2011 with fourteen ratios of nitrogen (N) and phosphorus (P2O5) fertilizers with constant potassium level (25 kg K2O ha-1) on groundnut cultivar TAG 24 at MARS, UAS, Dharwad. The dry pod yield increased due to increasing N/P ratios upto 0.78. The treatment receiving N/P fertilizer ratio of 0.57 (basal application of 20 kg N, 60 kg P2O5, 25 kg K2O ha-1 + foliar application of nitrogen @ 7 kg N ha-1 at 45 days after sowing and foliar application of nitrogen @ 7 kg N ha-1 at 60 days after sowing) recorded significantly higher dry pod yield (4361 kg ha-1), number of filled pods plant-1 (24.27), total number of pods plant-1 (29.53), 100 pod weight (1… | J48: C | K48: „UAS“ = University of Agricultural Sciences Dharwad | L48: C | N48: da
A49: 45 | B49: 2013 | C49: Air photography with use of unmanned aerial vehicle for solution of agriculture and cadastre tasks | D49: CyberLeninK (CyberLeninka) | E49: Environmental Sustainability and Technology | F49: https://openalex.org/W42328935 | H49: unmanned aerial | I49: Issues of information provision for agriculture and cadastre according to air photography materials from unmanned aerial vehicle are consider ed in the article. Materials of experimental air photography from air plane and copter were used. The work suggests technology of executing works on photography and processing of materials. Air photography parameters were proposed according to image qualit y and requirements for ground images resolutions for solving tasks of cadastre and agriculture. | J49: A | K49: UAV za poljoprivredu i katastar | L49: A | N49: da
A50: 46 | B50: 2012 | C50: A Path Planning Algorithm for UAV Based on Skeleton Algorithm | D50: Electronics Optics & Control | E50: Military Defense Systems Analysis | F50: https://openalex.org/W2363817629 | H50: uav, unmanned aerial | I50: The Unmanned Aerial Vehicle(UAV) will play a more and more important role in the futureand how to improve its survival-rate and operational effectiveness has become focus of the path-planning.The threat-circles were simplified from threats of radarantiaircraft missile landformno-fly areas and so onand a skeleton diagram was constructed based on the distribution of the threat-circles.The skeleton graph yielded the feasible paths for travel between a set of threat-circles to avoid the threats.The vector graphics were consisted of the lines whose cost was calculated out according to the specific information of threats.The initial optimal path was obtainedwhich was shortened according to t… | J50: B | K50: Planiranje putanje UAV-a (vojno) | L50: B | N50: da
A51: 47 | B51: 2015 | C51: Highways in the Sky: Scales of Atmospheric Transport of Plant Pathogens | D51: Annual Review of Phytopathology | E51: Plant Pathogens and Resistance | F51: https://openalex.org/W1918046236 | G51: https://doi.org/10.1146/annurev-phyto-080614-115942 | H51: drones, unmanned aircraft | I51: Many high-risk plant pathogens are transported over long distances (hundreds of meters to thousands of kilometers) in the atmosphere. The ability to track the movement of these pathogens in the atmosphere is essential for forecasting disease spread and establishing effective quarantine measures. Here, we discuss the scales of atmospheric dispersal of plant pathogens along a transport continuum (pathogen scale, farm scale, regional scale, and continental scale). Growers can use risk information at each of these dispersal scales to assist in making plant disease management decisions, such as the timely application of appropriate pesticides. Regional- and continental-scale atmospheric features … | J51: A | K51: Uzorkovanje patogena biljaka UAS-om | L51: A | N51: da
A52: 48 | B52: 2014 | C52: Control of VTOL vehicles with thrust-tilting augmentation | D52: Automatica | E52: Adaptive Control of Nonlinear Systems | F52: https://openalex.org/W2034953796 | G52: https://doi.org/10.1016/j.automatica.2014.10.129 | H52: (nije u naslovu/sažetku) | I52: (sažetak nije dostupan — otvoriti poveznicu) | J52: B | K52: VTOL vozila (pojam nije u sažetku) | L52: B | N52: da
A53: 49 | B53: 2013 | C53: FEATURES OF THE USE OF UNMANNED AERIAL VEHICLES FOR AGRICULTURE APPLICATIONS | D53: Aviation | E53: UAV Applications and Optimization | F53: https://openalex.org/W2017278113 | G53: https://doi.org/10.3846/16487788.2013.861224 | H53: uav, uavs, unmanned aerial | I53: Micro-UAVs (unmanned aerial vehicles) with a total weight below 5 kg are interesting alternative carriers for agricultural applications. Compared to standard airborne aerial surveys, UAVs are much more flexible and weather independent. As a result, micro-UAV surveys will pave the way for affordable, current and accurate geo-information. This article deals with the general conditions and challenges for unmanned aerial vehicles that can be used for agricultural land monitoring. The article includes an overview of the structural characteristics and parameters of a UAV that has been developed for environmental monitoring by the Institute of Transport Vehicle Technology of Riga Technical Universi… | J53: A | K53: UAV za poljoprivredne primjene | L53: A | N53: da
A54: 50 | B54: 2012 | C54: Integrated Planning and Control of Rotary-wing Unmanned Aerial Vehicle Navigation | D54: Journal of Aerospace Computing Information and Communication | E54: Robotic Path Planning Algorithms | F54: https://openalex.org/W2028262445 | G54: https://doi.org/10.2514/1.53862 | H54: unmanned aerial | I54: This paper presents an integrated planning and control algorithm for the navigation of an autonomous rotarywing unmanned aerial vehicle in a cluttered environment. The model predictive control combined with a potential fieldlike function integrates planning and control in a single step. This strategy enables the generation of dynamically feasible motion because the planning is done in the action space of the rotary-wing unmanned aerial vehicle. Moreover, it is able to respond promptly to abrupt changes in the environment because the reactive obstacleavoidance method only considers local sensory information. Finally, the shortsightedness of control-based reactive methods can be relieved by th… | J54: B | K54: Navigacija rotorskog UAV-a | L54: B | N54: da

Sheet Osjetljivost_upita
A1: Osjetljivost na definiciju upita (OpenAlex, dohvat 28. 8. 2026.): sirovi D AND A; čisti = sirovi NOT N (glavna serija); strogi = čisti NOT ekološki pojmovi
A3: Godina | B3: core_drone_agro_raw | C3: core_drone_agro (čisti) | D3: strict_noenv | E3: omjer čisti/sirovi | F3: omjer strogi/čisti
A4: 2005 | B4: 45 | C4: 29 | D4: 27 | E4: =C4/B4 -> 0.64444444 | F4: =D4/C4 -> 0.93103448
A5: 2006 | B5: 61 | C5: 38 | D5: 37 | E5: =C5/B5 -> 0.62295082 | F5: =D5/C5 -> 0.97368421
A6: 2007 | B6: 68 | C6: 48 | D6: 48 | E6: =C6/B6 -> 0.70588235 | F6: =D6/C6 -> 1
A7: 2008 | B7: 65 | C7: 39 | D7: 36 | E7: =C7/B7 -> 0.6 | F7: =D7/C7 -> 0.92307692
A8: 2009 | B8: 98 | C8: 57 | D8: 51 | E8: =C8/B8 -> 0.58163265 | F8: =D8/C8 -> 0.89473684
A9: 2010 | B9: 100 | C9: 62 | D9: 59 | E9: =C9/B9 -> 0.62 | F9: =D9/C9 -> 0.9516129
A10: 2011 | B10: 101 | C10: 80 | D10: 71 | E10: =C10/B10 -> 0.79207921 | F10: =D10/C10 -> 0.8875
A11: 2012 | B11: 174 | C11: 126 | D11: 112 | E11: =C11/B11 -> 0.72413793 | F11: =D11/C11 -> 0.88888889
A12: 2013 | B12: 217 | C12: 171 | D12: 141 | E12: =C12/B12 -> 0.78801843 | F12: =D12/C12 -> 0.8245614
A13: 2014 | B13: 277 | C13: 233 | D13: 204 | E13: =C13/B13 -> 0.84115523 | F13: =D13/C13 -> 0.87553648
A14: 2015 | B14: 371 | C14: 309 | D14: 275 | E14: =C14/B14 -> 0.8328841 | F14: =D14/C14 -> 0.88996764
A15: 2016 | B15: 498 | C15: 435 | D15: 386 | E15: =C15/B15 -> 0.87349398 | F15: =D15/C15 -> 0.88735632
... A24: 2025 | B24: 4525 | C24: 4381 | D24: 3529 | E24: =C24/B24 -> 0.9681768 | F24: =D24/C24 -> 0.80552385
A26: CAGR 2005–2025 | B26: =(B24/B4)^(1/20)-1 -> 0.25927419 | C26: =(C24/C4)^(1/20)-1 -> 0.28516462 | D26: =(D24/D4)^(1/20)-1 -> 0.27589341
A27: CAGR 2015–2025 | B27: =(B24/B14)^(1/10)-1 -> 0.28417576 | C27: =(C24/C14)^(1/10)-1 -> 0.30365141 | D27: =(D24/D14)^(1/10)-1 -> 0.29071957
A29: N = (drosophila OR gal4 OR transgene OR transgenic OR bee OR bees OR honeybee OR honeybees OR "honey bee" OR bumblebee OR apis OR urticaria OR aneurysm OR aneurysms OR patients OR "university of agricultural sciences"); ekološki pojmovi = (forest OR forests OR forestry OR wildlife OR ecology OR ecological OR biodiversity OR habitat OR wetland OR wetlands OR "protected area" OR wildfire OR marine OR coastal).
